Workbook

Sheet Optimization_Notes
A1: Refinery Production Planning – Optimization Notes (Objective Function & Constraints)
A2: Multi-period LP: 31 days (Oct 2026), 4 crudes, CDU → Reformer / RFCC / DHT, 10 tanks. Days 1–11 actual (locked), days 12–31 to optimise.
A5: 1. PURPOSE & WORKFLOW
A6: This workbook is a test-bed for a Python optimizer. Excel holds the data, the current (manual) plan and all checks; Python reads the data, solves for the best plan, and writes the decision variables back into Daily_Plan. Excel then recalculates margins, tank balances and constraint checks so the optimizer result can be verified independently of the solver.
A7: Step 1 | B7: Read parameters: Crude_Data, Unit_Data, Product_Data, Tank_Master, Crude_Receipts, Product_Liftings.
A8: Step 2 | B8: Read Daily_Plan rows 5–35. Rows with Status = 'Actual' are fixed history; rows with Status = 'Plan' are free.
A9: Step 3 | B9: Build and solve the LP below (scipy.optimize.linprog / HiGHS, PuLP or Pyomo all work).
A10: Step 4 | B10: Write optimal x, r, f into Daily_Plan!D:I for Plan rows only (green cells).
A11: Step 5 | B11: Open in Excel → check Constraint_Check!X37 = 0 and compare Daily_Plan KPI 'Plan-days margin' against the benchmark in section 9.
A13: 2. COLOUR LEGEND
B14: Blue text, yellow fill | C14: Parameter / input – edit to run scenarios
B15: Blue text, green fill | C15: Decision variable – optimizer writes here (Daily_Plan Plan rows)
B16: Blue text, grey fill | C16: Actual (locked) day – do not optimise
B17: Black text | C17: Formula / calculation
B18: Green text | C18: Link to another worksheet
A20: 3. SETS & INDICES
B21: Symbol | C21: Meaning | D21: Members / Excel source
B22: t ∈ T | C22: Day of horizon | D22: 1…31 (Daily_Plan col A). T_plan = days with Status 'Plan' (12…31)
B23: c ∈ C | C23: Crude grade | D23: Arab Light, Murban, Tapis, Kimanis (Crude_Data C3:F3)
B24: p ∈ P | C24: Finished product | D24: LPG, Naphtha, Gasoline 95, Jet A-1, Diesel B10, Fuel Oil (Product_Data C3:H3)
B25: k ∈ K | C25: Tank | D25: 4 crude tanks + 6 product tanks (Tank_Master A4:A13)
A27: 4. DECISION VARIABLES (per plan day t, units kbbl/d)
B28: Variable | C28: Meaning | D28: Excel location | E28: Bounds
B29: x[c,t] | C29: Crude c charged to the CDU | D29: Daily_Plan!D:G | E29: 0 … Xmax_c
B30: r[t] | C30: SR naphtha routed to the Reformer (rest sold as Naphtha) | D30: Daily_Plan!H | E30: Rmin … Rmax
B31: f[t] | C31: Atmospheric residue routed to the RFCC (rest goes to Fuel Oil) | D31: Daily_Plan!I | E31: Fmin … Fmax
B32: I[k,t] | C32: Closing inventory of tank k (state variable, can be eliminated by substitution) | D32: Tank_Balance!I | E32: Min heel … Capacity
A33: Total: 6 free variables × 20 plan days = 120 decision variables (+ 200 inventory states if modelled explicitly).
A35: 5. DERIVED FLOWS (all linear in x, r, f – see Daily_Plan formulas)
B36: Quantity | C36: Expression | D36: Excel column
B37: CDU_t | C37: Σc x[c,t] | D37: Daily_Plan!J
B38: Cut_j,t (j = LPG, Naph, Kero, GO, AR) | C38: Σc y[c,j] · x[c,t] | D38: Daily_Plan!K:O
B39: DHT_t | C39: GO_t + yLCO · f[t] | D39: Daily_Plan!W
B40: LPG_t | C40: LPG_SR,t + yRef,LPG · r[t] + yFCC,LPG · f[t] | D40: Daily_Plan!X
B41: Naphtha_t | C41: Naph_t − r[t] | D41: Daily_Plan!Y
B42: Gasoline_t | C42: yRef,Reformate · r[t] + yFCC,Gasoline · f[t] | D42: Daily_Plan!Z
B43: Jet_t | C43: Kero_t | D43: Daily_Plan!AA
B44: Diesel_t | C44: yDHT · DHT_t | D44: Daily_Plan!AB
B45: FuelOil_t | C45: AR_t − f[t] + ySlurry · f[t] | D45: Daily_Plan!AC
A47: 6. OBJECTIVE FUNCTION – maximise gross margin over plan days ($k)
A48: max Z = Σ(t∈T_plan) [ Σp Price_p · Prod[p,t] − Σc CrudePrice_c · x[c,t] − ( OpexCDU · CDU_t + OpexRef · r[t] + OpexRFCC · f[t] + OpexDHT · DHT_t ) ]
B49: Term | C49: Meaning | D49: Excel source
B50: Revenue | C50: Product make valued at netback price (production-based valuation) | D50: Daily_Plan!AE ← Product_Data row 4
B51: Crude cost | C51: Delivered crude price × crude charged | D51: Daily_Plan!AF ← Crude_Data row 4
B52: Opex | C52: Variable operating cost per bbl of unit feed | D52: Daily_Plan!AG ← Unit_Data D7, D10, D16, D24
B53: Z | C53: Plan-days gross margin (actual days are constant and excluded) | D53: Daily_Plan KPI 'Plan-days margin'
A54: Tip: because every product is linear in (x, r, f), the objective collapses to a constant margin coefficient per variable – e.g. Z = Σt (m_c · x[c,t] + m_r · r[t] + m_f · f[t]). Compute m from the Excel parameters; it shows instantly which crude/unit is most valuable and why the solver pushes against certain limits.
A56: 7. CONSTRAINTS (✓ = checked live in Constraint_Check)
A57: ID | B57: Constraint | C57: Mathematical form (for every plan day t unless noted) | D57: Parameter source | E57: Type
A58: C1 | B58: CDU capacity / turndown | C58: CDUmin ≤ Σc x[c,t] ≤ CDUmax | D58: Unit_Data D4:D5 | E58: Capacity ✓
A59: C2 | B59: Crude rate limits | C59: Xmin_c ≤ x[c,t] ≤ Xmax_c | D59: Crude_Data row 13–14 | E59: Bound ✓
A60: C3 | B60: CDU ramp rate | C60: −Ramp ≤ CDU_t − CDU_(t−1) ≤ Ramp (day 12 is linked to actual day 11) | D60: Unit_Data D6 | E60: Operability ✓
A61: C4 | B61: Reformer capacity | C61: Rmin ≤ r[t] ≤ Rmax | D61: Unit_Data D8:D9 | E61: Capacity ✓
A62: C5 | B62: Naphtha availability | C62: r[t] ≤ Σc yNaph,c · x[c,t] (Naphtha sales ≥ 0) | D62: Crude_Data row 6 | E62: Mass balance ✓
A63: C6 | B63: RFCC capacity | C63: Fmin ≤ f[t] ≤ Fmax | D63: Unit_Data D14:D15 | E63: Capacity ✓
A64: C7 | B64: Residue availability | C64: f[t] ≤ Σc yAR,c · x[c,t] (Fuel Oil ≥ 0) | D64: Crude_Data row 9 | E64: Mass balance ✓
A65: C8 | B65: DHT capacity | C65: DHTmin ≤ Σc yGO,c · x[c,t] + yLCO · f[t] ≤ DHTmax | D65: Unit_Data D22:D23 | E65: Capacity ✓
A66: C9 | B66: Gasoline RON spec | C66: (RONref − RONspec) · yRef · r[t] + (RONfcc − RONspec) · yFCC · f[t] ≥ 0 (linearised blend) | D66: Unit_Data D26:D28 | E66: Quality ✓
A67: C10 | B67: Residue sulfur spec | C67: Σc yAR,c · (S_c − Smax) · x[c,t] ≤ 0 (linearised blend) | D67: Crude_Data row 12, Unit_Data D29 | E67: Quality ✓
A68: C11 | B68: Crude tank balance | C68: I[c,t] = I[c,t−1] + Receipt[c,t] − x[c,t] | D68: Crude_Receipts, Tank_Master F | E68: Material balance
... A73: C16 | B73: Non-negativity | C73: x, r, f, I ≥ 0 | D73: - | E73: Bound
A74: Why C9 and C10 are linear: a ratio spec such as (Σ q_i·v_i)/(Σ v_i) ≥ spec is multiplied through by the (positive) pool volume, giving Σ (q_i − spec)·v_i ≥ 0. This keeps the whole model an LP – no NLP solver needed.
A76: 8. KEY ASSUMPTIONS & SIMPLIFICATIONS
A77: • Fixed (linear) yields – no cut-point, severity or conversion optimisation. Upgrade path: delta-base vectors or swing cuts.
A78: • Volumetric blending for RON and sulfur (sulfur should strictly be mass-weighted; acceptable for a test model).
A79: • Products valued on production (netback); liftings and crude receipts are fixed schedules, so tanks absorb the imbalance.
A80: • Crude and product tanks are aggregated per grade/product (one tank group each).
A81: • Single day time-step; no unit shutdowns, catalyst cycle or maintenance windows modelled.
A82: • All prices, yields and capacities are illustrative values for testing only.
A84: 9. BENCHMARK – use this to validate your Python optimizer
B85: Item | C85: Value ($k) | D85: How obtained
B86: Original manual plan – plan days 12–31 | C86: 17024.9 | D86: Daily_Plan values as delivered in this file
B87: Reference LP optimum – plan days 12–31 | C87: 18320 | D87: scipy.optimize.linprog (HiGHS), solved at file creation on the baseline data
B88: Reference uplift (optimum − original) | C88: =C87-C86 -> 1295.1 | D88: Value of optimisation over 20 plan days
B89: Current plan in Daily_Plan – plan days | C89: =Daily_Plan!G41 -> 17024.88 | D89: Live – updates when the optimizer writes results
B90: Gap: LP optimum − current plan | C90: =C87-C89 -> 1295.12 | D90: ≈ 0 when your optimizer matches the reference
A91: A correct optimizer should reach ≈ 18,320 $k with Constraint_Check!X37 = 0. The LP optimum is degenerate (several plans give the same margin), so your crude split may differ from someone else's while the objective value matches. Typical binding constraints: CDU max, Reformer max, RFCC max, residue sulfur (C10), crude tank min-heel and end-of-month targets.

Sheet Daily_Plan
A1: Refinery Daily Production Plan – October 2026 (kbbl/d, $k/d)
A2: Days 1–11 = ACTUAL (locked). Days 12–31 = PLAN. Green cells = decision variables the Python optimizer writes back; everything else is calculated.
D3: DECISION VARIABLES (kbbl/d) | J3: CDU – straight-run cuts | Q3: Reformer | S3: RFCC | W3: DHT | X3: Product make (kbbl/d) | AD3: Quality | AE3: Economics ($k/d)
A4: Day | B4: Date | C4: Status | D4: Crude: Arab Light | E4: Crude: Murban | F4: Crude: Tapis | G4: Crude: Kimanis | H4: Reformer feed | I4: RFCC feed | J4: CDU total | K4: SR LPG | L4: SR Naphtha | M4: SR Kerosene | N4: SR Gasoil | O4: Atm Residue | P4: Residue S (wt%) | Q4: Reformate | R4: Reformer LPG | S4: FCC gasoline | T4: FCC LPG | U4: LCO | V4: Slurry | W4: DHT feed | X4: LPG | Y4: Naphtha | Z4: Gasoline 95 | AA4: Jet A-1 | AB4: Diesel B10 | AC4: Fuel Oil | AD4: Gasoline RON | AE4: Product revenue | AF4: Crude cost | AG4: Opex | AH4: Gross margin | AI4: Margin $/bbl crude
A5: 1 | B5: 46296 | C5: Actual | D5: 40 | E5: 40 | F5: 40 | G5: 30 | H5: 22 | I5: 32 | J5: =SUM(D5:G5) -> 150 | K5: =SUMPRODUCT($D5:$G5,Crude_Data!$C$5:$F$5) -> 3.8 | L5: =SUMPRODUCT($D5:$G5,Crude_Data!$C$6:$F$6) -> 31.6 | M5: =SUMPRODUCT($D5:$G5,Crude_Data!$C$7:$F$7) -> 23.3 | N5: =SUMPRODUCT($D5:$G5,Crude_Data!$C$8:$F$8) -> 38.4 | O5: =SUMPRODUCT($D5:$G5,Crude_Data!$C$9:$F$9) -> 51.4 | P5: =IF(O5>0,SUMPRODUCT($D5:$G5,Crude_Data!$C$9:$F$9,Crude_Data!$C$12:$F$12)/O5,0) -> 1.4610895 | Q5: =H5*Unit_Data!$D$11 -> 18.48 | R5: =H5*Unit_Data!$D$12 -> 1.76 | S5: =I5*Unit_Data!$D$17 -> 16.64 | T5: =I5*Unit_Data!$D$18 -> 5.76 | U5: =I5*Unit_Data!$D$19 -> 5.76 | V5: =I5*Unit_Data!$D$20 -> 1.92 | W5: =N5+U5 -> 44.16 | X5: =K5+R5+T5 -> 11.32 | Y5: =L5-H5 -> 9.6 | Z5: =Q5+S5 -> 35.12 | AA5: =M5 -> 23.3 | AB5: =W5*Unit_Data!$D$25 -> 43.2768 | AC5: =O5-I5+V5 -> 21.32 | AD5: =IF(Z5>0,(Q5*Unit_Data!$D$26+S5*Unit_Data!$D$27)/Z5,0) -> 95.157175 | AE5: =SUMPRODUCT(X5:AC5,Product_Data!$C$4:$H$4) -> 13345.484 | AF5: =SUMPRODUCT(D5:G5,Crude_Data!$C$4:$F$4) -> 12095 | AG5: =J5*Unit_Data!$D$7+H5*Unit_Data!$D$10+I5*Unit_Data!$D$16+W5*Unit_Data!$D$24 -> 399.24 | AH5: =AE5-AF5-AG5 -> 851.244 | AI5: =IF(J5>0,AH5/J5,0) -> 5.67496
A6: 2 | B6: 46297 | C6: Actual | D6: 40 | E6: 40 | F6: 40 | G6: 30 | H6: 22 | I6: 32 | J6: =SUM(D6:G6) -> 150 | K6: =SUMPRODUCT($D6:$G6,Crude_Data!$C$5:$F$5) -> 3.8 | L6: =SUMPRODUCT($D6:$G6,Crude_Data!$C$6:$F$6) -> 31.6 | M6: =SUMPRODUCT($D6:$G6,Crude_Data!$C$7:$F$7) -> 23.3 | N6: =SUMPRODUCT($D6:$G6,Crude_Data!$C$8:$F$8) -> 38.4 | O6: =SUMPRODUCT($D6:$G6,Crude_Data!$C$9:$F$9) -> 51.4 | P6: =IF(O6>0,SUMPRODUCT($D6:$G6,Crude_Data!$C$9:$F$9,Crude_Data!$C$12:$F$12)/O6,0) -> 1.4610895 | Q6: =H6*Unit_Data!$D$11 -> 18.48 | R6: =H6*Unit_Data!$D$12 -> 1.76 | S6: =I6*Unit_Data!$D$17 -> 16.64 | T6: =I6*Unit_Data!$D$18 -> 5.76 | U6: =I6*Unit_Data!$D$19 -> 5.76 | V6: =I6*Unit_Data!$D$20 -> 1.92 | W6: =N6+U6 -> 44.16 | X6: =K6+R6+T6 -> 11.32 | Y6: =L6-H6 -> 9.6 | Z6: =Q6+S6 -> 35.12 | AA6: =M6 -> 23.3 | AB6: =W6*Unit_Data!$D$25 -> 43.2768 | AC6: =O6-I6+V6 -> 21.32 | AD6: =IF(Z6>0,(Q6*Unit_Data!$D$26+S6*Unit_Data!$D$27)/Z6,0) -> 95.157175 | AE6: =SUMPRODUCT(X6:AC6,Product_Data!$C$4:$H$4) -> 13345.484 | AF6: =SUMPRODUCT(D6:G6,Crude_Data!$C$4:$F$4) -> 12095 | AG6: =J6*Unit_Data!$D$7+H6*Unit_Data!$D$10+I6*Unit_Data!$D$16+W6*Unit_Data!$D$24 -> 399.24 | AH6: =AE6-AF6-AG6 -> 851.244 | AI6: =IF(J6>0,AH6/J6,0) -> 5.67496
A7: 3 | B7: 46298 | C7: Actual | D7: 41 | E7: 38 | F7: 41 | G7: 30 | H7: 23 | I7: 33 | J7: =SUM(D7:G7) -> 150 | K7: =SUMPRODUCT($D7:$G7,Crude_Data!$C$5:$F$5) -> 3.79 | L7: =SUMPRODUCT($D7:$G7,Crude_Data!$C$6:$F$6) -> 31.52 | M7: =SUMPRODUCT($D7:$G7,Crude_Data!$C$7:$F$7) -> 23.29 | N7: =SUMPRODUCT($D7:$G7,Crude_Data!$C$8:$F$8) -> 38.46 | O7: =SUMPRODUCT($D7:$G7,Crude_Data!$C$9:$F$9) -> 51.44 | P7: =IF(O7>0,SUMPRODUCT($D7:$G7,Crude_Data!$C$9:$F$9,Crude_Data!$C$12:$F$12)/O7,0) -> 1.4697998 | Q7: =H7*Unit_Data!$D$11 -> 19.32 | R7: =H7*Unit_Data!$D$12 -> 1.84 | S7: =I7*Unit_Data!$D$17 -> 17.16 | T7: =I7*Unit_Data!$D$18 -> 5.94 | U7: =I7*Unit_Data!$D$19 -> 5.94 | V7: =I7*Unit_Data!$D$20 -> 1.98 | W7: =N7+U7 -> 44.4 | X7: =K7+R7+T7 -> 11.57 | Y7: =L7-H7 -> 8.52 | Z7: =Q7+S7 -> 36.48 | AA7: =M7 -> 23.29 | AB7: =W7*Unit_Data!$D$25 -> 43.512 | AC7: =O7-I7+V7 -> 20.42 | AD7: =IF(Z7>0,(Q7*Unit_Data!$D$26+S7*Unit_Data!$D$27)/Z7,0) -> 95.177632 | AE7: =SUMPRODUCT(X7:AC7,Product_Data!$C$4:$H$4) -> 13374.07 | AF7: =SUMPRODUCT(D7:G7,Crude_Data!$C$4:$F$4) -> 12094 | AG7: =J7*Unit_Data!$D$7+H7*Unit_Data!$D$10+I7*Unit_Data!$D$16+W7*Unit_Data!$D$24 -> 406.1 | AH7: =AE7-AF7-AG7 -> 873.97 | AI7: =IF(J7>0,AH7/J7,0) -> 5.8264667
A8: 4 | B8: 46299 | C8: Actual | D8: 39 | E8: 36 | F8: 39 | G8: 28 | H8: 21 | I8: 30 | J8: =SUM(D8:G8) -> 142 | K8: =SUMPRODUCT($D8:$G8,Crude_Data!$C$5:$F$5) -> 3.59 | L8: =SUMPRODUCT($D8:$G8,Crude_Data!$C$6:$F$6) -> 29.84 | M8: =SUMPRODUCT($D8:$G8,Crude_Data!$C$7:$F$7) -> 22.05 | N8: =SUMPRODUCT($D8:$G8,Crude_Data!$C$8:$F$8) -> 36.38 | O8: =SUMPRODUCT($D8:$G8,Crude_Data!$C$9:$F$9) -> 48.72 | P8: =IF(O8>0,SUMPRODUCT($D8:$G8,Crude_Data!$C$9:$F$9,Crude_Data!$C$12:$F$12)/O8,0) -> 1.4741687 | Q8: =H8*Unit_Data!$D$11 -> 17.64 | R8: =H8*Unit_Data!$D$12 -> 1.68 | S8: =I8*Unit_Data!$D$17 -> 15.6 | T8: =I8*Unit_Data!$D$18 -> 5.4 | U8: =I8*Unit_Data!$D$19 -> 5.4 | V8: =I8*Unit_Data!$D$20 -> 1.8 | W8: =N8+U8 -> 41.78 | X8: =K8+R8+T8 -> 10.67 | Y8: =L8-H8 -> 8.84 | Z8: =Q8+S8 -> 33.24 | AA8: =M8 -> 22.05 | AB8: =W8*Unit_Data!$D$25 -> 40.9444 | AC8: =O8-I8+V8 -> 20.52 | AD8: =IF(Z8>0,(Q8*Unit_Data!$D$26+S8*Unit_Data!$D$27)/Z8,0) -> 95.184116 | AE8: =SUMPRODUCT(X8:AC8,Product_Data!$C$4:$H$4) -> 12632.872 | AF8: =SUMPRODUCT(D8:G8,Crude_Data!$C$4:$F$4) -> 11448 | AG8: =J8*Unit_Data!$D$7+H8*Unit_Data!$D$10+I8*Unit_Data!$D$16+W8*Unit_Data!$D$24 -> 377.17 | AH8: =AE8-AF8-AG8 -> 807.702 | AI8: =IF(J8>0,AH8/J8,0) -> 5.6880423
A9: 5 | B9: 46300 | C9: Actual | D9: 35 | E9: 34 | F9: 37 | G9: 26 | H9: 19 | I9: 28 | J9: =SUM(D9:G9) -> 132 | K9: =SUMPRODUCT($D9:$G9,Crude_Data!$C$5:$F$5) -> 3.35 | L9: =SUMPRODUCT($D9:$G9,Crude_Data!$C$6:$F$6) -> 27.8 | M9: =SUMPRODUCT($D9:$G9,Crude_Data!$C$7:$F$7) -> 20.53 | N9: =SUMPRODUCT($D9:$G9,Crude_Data!$C$8:$F$8) -> 33.9 | O9: =SUMPRODUCT($D9:$G9,Crude_Data!$C$9:$F$9) -> 45.1 | P9: =IF(O9>0,SUMPRODUCT($D9:$G9,Crude_Data!$C$9:$F$9,Crude_Data!$C$12:$F$12)/O9,0) -> 1.4487029 | Q9: =H9*Unit_Data!$D$11 -> 15.96 | R9: =H9*Unit_Data!$D$12 -> 1.52 | S9: =I9*Unit_Data!$D$17 -> 14.56 | T9: =I9*Unit_Data!$D$18 -> 5.04 | U9: =I9*Unit_Data!$D$19 -> 5.04 | V9: =I9*Unit_Data!$D$20 -> 1.68 | W9: =N9+U9 -> 38.94 | X9: =K9+R9+T9 -> 9.91 | Y9: =L9-H9 -> 8.8 | Z9: =Q9+S9 -> 30.52 | AA9: =M9 -> 20.53 | AB9: =W9*Unit_Data!$D$25 -> 38.1612 | AC9: =O9-I9+V9 -> 18.78 | AD9: =IF(Z9>0,(Q9*Unit_Data!$D$26+S9*Unit_Data!$D$27)/Z9,0) -> 95.137615 | AE9: =SUMPRODUCT(X9:AC9,Product_Data!$C$4:$H$4) -> 11740.956 | AF9: =SUMPRODUCT(D9:G9,Crude_Data!$C$4:$F$4) -> 10650 | AG9: =J9*Unit_Data!$D$7+H9*Unit_Data!$D$10+I9*Unit_Data!$D$16+W9*Unit_Data!$D$24 -> 349.91 | AH9: =AE9-AF9-AG9 -> 741.046 | AI9: =IF(J9>0,AH9/J9,0) -> 5.6139848
A10: 6 | B10: 46301 | C10: Actual | D10: 37 | E10: 36 | F10: 38 | G10: 28 | H10: 20 | I10: 30 | J10: =SUM(D10:G10) -> 139 | K10: =SUMPRODUCT($D10:$G10,Crude_Data!$C$5:$F$5) -> 3.52 | L10: =SUMPRODUCT($D10:$G10,Crude_Data!$C$6:$F$6) -> 29.26 | M10: =SUMPRODUCT($D10:$G10,Crude_Data!$C$7:$F$7) -> 21.6 | N10: =SUMPRODUCT($D10:$G10,Crude_Data!$C$8:$F$8) -> 35.68 | O10: =SUMPRODUCT($D10:$G10,Crude_Data!$C$9:$F$9) -> 47.55 | P10: =IF(O10>0,SUMPRODUCT($D10:$G10,Crude_Data!$C$9:$F$9,Crude_Data!$C$12:$F$12)/O10,0) -> 1.4528076 | Q10: =H10*Unit_Data!$D$11 -> 16.8 | R10: =H10*Unit_Data!$D$12 -> 1.6 | S10: =I10*Unit_Data!$D$17 -> 15.6 | T10: =I10*Unit_Data!$D$18 -> 5.4 | U10: =I10*Unit_Data!$D$19 -> 5.4 | V10: =I10*Unit_Data!$D$20 -> 1.8 | W10: =N10+U10 -> 41.08 | X10: =K10+R10+T10 -> 10.52 | Y10: =L10-H10 -> 9.26 | Z10: =Q10+S10 -> 32.4 | AA10: =M10 -> 21.6 | AB10: =W10*Unit_Data!$D$25 -> 40.2584 | AC10: =O10-I10+V10 -> 19.35 | AD10: =IF(Z10>0,(Q10*Unit_Data!$D$26+S10*Unit_Data!$D$27)/Z10,0) -> 95.111111 | AE10: =SUMPRODUCT(X10:AC10,Product_Data!$C$4:$H$4) -> 12369.172 | AF10: =SUMPRODUCT(D10:G10,Crude_Data!$C$4:$F$4) -> 11212 | AG10: =J10*Unit_Data!$D$7+H10*Unit_Data!$D$10+I10*Unit_Data!$D$16+W10*Unit_Data!$D$24 -> 370.62 | AH10: =AE10-AF10-AG10 -> 786.552 | AI10: =IF(J10>0,AH10/J10,0) -> 5.6586475
A11: 7 | B11: 46302 | C11: Actual | D11: 39 | E11: 38 | F11: 40 | G11: 30 | H11: 22 | I11: 32 | J11: =SUM(D11:G11) -> 147 | K11: =SUMPRODUCT($D11:$G11,Crude_Data!$C$5:$F$5) -> 3.72 | L11: =SUMPRODUCT($D11:$G11,Crude_Data!$C$6:$F$6) -> 30.94 | M11: =SUMPRODUCT($D11:$G11,Crude_Data!$C$7:$F$7) -> 22.84 | N11: =SUMPRODUCT($D11:$G11,Crude_Data!$C$8:$F$8) -> 37.76 | O11: =SUMPRODUCT($D11:$G11,Crude_Data!$C$9:$F$9) -> 50.27 | P11: =IF(O11>0,SUMPRODUCT($D11:$G11,Crude_Data!$C$9:$F$9,Crude_Data!$C$12:$F$12)/O11,0) -> 1.4494927 | Q11: =H11*Unit_Data!$D$11 -> 18.48 | R11: =H11*Unit_Data!$D$12 -> 1.76 | S11: =I11*Unit_Data!$D$17 -> 16.64 | T11: =I11*Unit_Data!$D$18 -> 5.76 | U11: =I11*Unit_Data!$D$19 -> 5.76 | V11: =I11*Unit_Data!$D$20 -> 1.92 | W11: =N11+U11 -> 43.52 | X11: =K11+R11+T11 -> 11.24 | Y11: =L11-H11 -> 8.94 | Z11: =Q11+S11 -> 35.12 | AA11: =M11 -> 22.84 | AB11: =W11*Unit_Data!$D$25 -> 42.6496 | AC11: =O11-I11+V11 -> 20.19 | AD11: =IF(Z11>0,(Q11*Unit_Data!$D$26+S11*Unit_Data!$D$27)/Z11,0) -> 95.157175 | AE11: =SUMPRODUCT(X11:AC11,Product_Data!$C$4:$H$4) -> 13097.248 | AF11: =SUMPRODUCT(D11:G11,Crude_Data!$C$4:$F$4) -> 11858 | AG11: =J11*Unit_Data!$D$7+H11*Unit_Data!$D$10+I11*Unit_Data!$D$16+W11*Unit_Data!$D$24 -> 395.28 | AH11: =AE11-AF11-AG11 -> 843.968 | AI11: =IF(J11>0,AH11/J11,0) -> 5.7412789
A12: 8 | B12: 46303 | C12: Actual | D12: 40 | E12: 40 | F12: 40 | G12: 30 | H12: 22 | I12: 33 | J12: =SUM(D12:G12) -> 150 | K12: =SUMPRODUCT($D12:$G12,Crude_Data!$C$5:$F$5) -> 3.8 | L12: =SUMPRODUCT($D12:$G12,Crude_Data!$C$6:$F$6) -> 31.6 | M12: =SUMPRODUCT($D12:$G12,Crude_Data!$C$7:$F$7) -> 23.3 | N12: =SUMPRODUCT($D12:$G12,Crude_Data!$C$8:$F$8) -> 38.4 | O12: =SUMPRODUCT($D12:$G12,Crude_Data!$C$9:$F$9) -> 51.4 | P12: =IF(O12>0,SUMPRODUCT($D12:$G12,Crude_Data!$C$9:$F$9,Crude_Data!$C$12:$F$12)/O12,0) -> 1.4610895 | Q12: =H12*Unit_Data!$D$11 -> 18.48 | R12: =H12*Unit_Data!$D$12 -> 1.76 | S12: =I12*Unit_Data!$D$17 -> 17.16 | T12: =I12*Unit_Data!$D$18 -> 5.94 | U12: =I12*Unit_Data!$D$19 -> 5.94 | V12: =I12*Unit_Data!$D$20 -> 1.98 | W12: =N12+U12 -> 44.34 | X12: =K12+R12+T12 -> 11.5 | Y12: =L12-H12 -> 9.6 | Z12: =Q12+S12 -> 35.64 | AA12: =M12 -> 23.3 | AB12: =W12*Unit_Data!$D$25 -> 43.4532 | AC12: =O12-I12+V12 -> 20.38 | AD12: =IF(Z12>0,(Q12*Unit_Data!$D$26+S12*Unit_Data!$D$27)/Z12,0) -> 95.111111 | AE12: =SUMPRODUCT(X12:AC12,Product_Data!$C$4:$H$4) -> 13358.606 | AF12: =SUMPRODUCT(D12:G12,Crude_Data!$C$4:$F$4) -> 12095 | AG12: =J12*Unit_Data!$D$7+H12*Unit_Data!$D$10+I12*Unit_Data!$D$16+W12*Unit_Data!$D$24 -> 403.51 | AH12: =AE12-AF12-AG12 -> 860.096 | AI12: =IF(J12>0,AH12/J12,0) -> 5.7339733
A13: 9 | B13: 46304 | C13: Actual | D13: 40 | E13: 40 | F13: 41 | G13: 29 | H13: 23 | I13: 33 | J13: =SUM(D13:G13) -> 150 | K13: =SUMPRODUCT($D13:$G13,Crude_Data!$C$5:$F$5) -> 3.81 | L13: =SUMPRODUCT($D13:$G13,Crude_Data!$C$6:$F$6) -> 31.62 | M13: =SUMPRODUCT($D13:$G13,Crude_Data!$C$7:$F$7) -> 23.32 | N13: =SUMPRODUCT($D13:$G13,Crude_Data!$C$8:$F$8) -> 38.38 | O13: =SUMPRODUCT($D13:$G13,Crude_Data!$C$9:$F$9) -> 51.37 | P13: =IF(O13>0,SUMPRODUCT($D13:$G13,Crude_Data!$C$9:$F$9,Crude_Data!$C$12:$F$12)/O13,0) -> 1.4615632 | Q13: =H13*Unit_Data!$D$11 -> 19.32 | R13: =H13*Unit_Data!$D$12 -> 1.84 | S13: =I13*Unit_Data!$D$17 -> 17.16 | T13: =I13*Unit_Data!$D$18 -> 5.94 | U13: =I13*Unit_Data!$D$19 -> 5.94 | V13: =I13*Unit_Data!$D$20 -> 1.98 | W13: =N13+U13 -> 44.32 | X13: =K13+R13+T13 -> 11.59 | Y13: =L13-H13 -> 8.62 | Z13: =Q13+S13 -> 36.48 | AA13: =M13 -> 23.32 | AB13: =W13*Unit_Data!$D$25 -> 43.4336 | AC13: =O13-I13+V13 -> 20.35 | AD13: =IF(Z13>0,(Q13*Unit_Data!$D$26+S13*Unit_Data!$D$27)/Z13,0) -> 95.177632 | AE13: =SUMPRODUCT(X13:AC13,Product_Data!$C$4:$H$4) -> 13372.488 | AF13: =SUMPRODUCT(D13:G13,Crude_Data!$C$4:$F$4) -> 12096.5 | AG13: =J13*Unit_Data!$D$7+H13*Unit_Data!$D$10+I13*Unit_Data!$D$16+W13*Unit_Data!$D$24 -> 405.98 | AH13: =AE13-AF13-AG13 -> 870.008 | AI13: =IF(J13>0,AH13/J13,0) -> 5.8000533
A14: 10 | B14: 46305 | C14: Actual | D14: 40 | E14: 40 | F14: 40 | G14: 30 | H14: 22 | I14: 32 | J14: =SUM(D14:G14) -> 150 | K14: =SUMPRODUCT($D14:$G14,Crude_Data!$C$5:$F$5) -> 3.8 | L14: =SUMPRODUCT($D14:$G14,Crude_Data!$C$6:$F$6) -> 31.6 | M14: =SUMPRODUCT($D14:$G14,Crude_Data!$C$7:$F$7) -> 23.3 | N14: =SUMPRODUCT($D14:$G14,Crude_Data!$C$8:$F$8) -> 38.4 | O14: =SUMPRODUCT($D14:$G14,Crude_Data!$C$9:$F$9) -> 51.4 | P14: =IF(O14>0,SUMPRODUCT($D14:$G14,Crude_Data!$C$9:$F$9,Crude_Data!$C$12:$F$12)/O14,0) -> 1.4610895 | Q14: =H14*Unit_Data!$D$11 -> 18.48 | R14: =H14*Unit_Data!$D$12 -> 1.76 | S14: =I14*Unit_Data!$D$17 -> 16.64 | T14: =I14*Unit_Data!$D$18 -> 5.76 | U14: =I14*Unit_Data!$D$19 -> 5.76 | V14: =I14*Unit_Data!$D$20 -> 1.92 | W14: =N14+U14 -> 44.16 | X14: =K14+R14+T14 -> 11.32 | Y14: =L14-H14 -> 9.6 | Z14: =Q14+S14 -> 35.12 | AA14: =M14 -> 23.3 | AB14: =W14*Unit_Data!$D$25 -> 43.2768 | AC14: =O14-I14+V14 -> 21.32 | AD14: =IF(Z14>0,(Q14*Unit_Data!$D$26+S14*Unit_Data!$D$27)/Z14,0) -> 95.157175 | AE14: =SUMPRODUCT(X14:AC14,Product_Data!$C$4:$H$4) -> 13345.484 | AF14: =SUMPRODUCT(D14:G14,Crude_Data!$C$4:$F$4) -> 12095 | AG14: =J14*Unit_Data!$D$7+H14*Unit_Data!$D$10+I14*Unit_Data!$D$16+W14*Unit_Data!$D$24 -> 399.24 | AH14: =AE14-AF14-AG14 -> 851.244 | AI14: =IF(J14>0,AH14/J14,0) -> 5.67496
A15: 11 | B15: 46306 | C15: Actual | D15: 40 | E15: 40 | F15: 40 | G15: 30 | H15: 22 | I15: 32 | J15: =SUM(D15:G15) -> 150 | K15: =SUMPRODUCT($D15:$G15,Crude_Data!$C$5:$F$5) -> 3.8 | L15: =SUMPRODUCT($D15:$G15,Crude_Data!$C$6:$F$6) -> 31.6 | M15: =SUMPRODUCT($D15:$G15,Crude_Data!$C$7:$F$7) -> 23.3 | N15: =SUMPRODUCT($D15:$G15,Crude_Data!$C$8:$F$8) -> 38.4 | O15: =SUMPRODUCT($D15:$G15,Crude_Data!$C$9:$F$9) -> 51.4 | P15: =IF(O15>0,SUMPRODUCT($D15:$G15,Crude_Data!$C$9:$F$9,Crude_Data!$C$12:$F$12)/O15,0) -> 1.4610895 | Q15: =H15*Unit_Data!$D$11 -> 18.48 | R15: =H15*Unit_Data!$D$12 -> 1.76 | S15: =I15*Unit_Data!$D$17 -> 16.64 | T15: =I15*Unit_Data!$D$18 -> 5.76 | U15: =I15*Unit_Data!$D$19 -> 5.76 | V15: =I15*Unit_Data!$D$20 -> 1.92 | W15: =N15+U15 -> 44.16 | X15: =K15+R15+T15 -> 11.32 | Y15: =L15-H15 -> 9.6 | Z15: =Q15+S15 -> 35.12 | AA15: =M15 -> 23.3 | AB15: =W15*Unit_Data!$D$25 -> 43.2768 | AC15: =O15-I15+V15 -> 21.32 | AD15: =IF(Z15>0,(Q15*Unit_Data!$D$26+S15*Unit_Data!$D$27)/Z15,0) -> 95.157175 | AE15: =SUMPRODUCT(X15:AC15,Product_Data!$C$4:$H$4) -> 13345.484 | AF15: =SUMPRODUCT(D15:G15,Crude_Data!$C$4:$F$4) -> 12095 | AG15: =J15*Unit_Data!$D$7+H15*Unit_Data!$D$10+I15*Unit_Data!$D$16+W15*Unit_Data!$D$24 -> 399.24 | AH15: =AE15-AF15-AG15 -> 851.244 | AI15: =IF(J15>0,AH15/J15,0) -> 5.67496
A16: 12 | B16: 46307 | C16: Plan | D16: 40 | E16: 40 | F16: 40 | G16: 30 | H16: 22 | I16: 32 | J16: =SUM(D16:G16) -> 150 | K16: =SUMPRODUCT($D16:$G16,Crude_Data!$C$5:$F$5) -> 3.8 | L16: =SUMPRODUCT($D16:$G16,Crude_Data!$C$6:$F$6) -> 31.6 | M16: =SUMPRODUCT($D16:$G16,Crude_Data!$C$7:$F$7) -> 23.3 | N16: =SUMPRODUCT($D16:$G16,Crude_Data!$C$8:$F$8) -> 38.4 | O16: =SUMPRODUCT($D16:$G16,Crude_Data!$C$9:$F$9) -> 51.4 | P16: =IF(O16>0,SUMPRODUCT($D16:$G16,Crude_Data!$C$9:$F$9,Crude_Data!$C$12:$F$12)/O16,0) -> 1.4610895 | Q16: =H16*Unit_Data!$D$11 -> 18.48 | R16: =H16*Unit_Data!$D$12 -> 1.76 | S16: =I16*Unit_Data!$D$17 -> 16.64 | T16: =I16*Unit_Data!$D$18 -> 5.76 | U16: =I16*Unit_Data!$D$19 -> 5.76 | V16: =I16*Unit_Data!$D$20 -> 1.92 | W16: =N16+U16 -> 44.16 | X16: =K16+R16+T16 -> 11.32 | Y16: =L16-H16 -> 9.6 | Z16: =Q16+S16 -> 35.12 | AA16: =M16 -> 23.3 | AB16: =W16*Unit_Data!$D$25 -> 43.2768 | AC16: =O16-I16+V16 -> 21.32 | AD16: =IF(Z16>0,(Q16*Unit_Data!$D$26+S16*Unit_Data!$D$27)/Z16,0) -> 95.157175 | AE16: =SUMPRODUCT(X16:AC16,Product_Data!$C$4:$H$4) -> 13345.484 | AF16: =SUMPRODUCT(D16:G16,Crude_Data!$C$4:$F$4) -> 12095 | AG16: =J16*Unit_Data!$D$7+H16*Unit_Data!$D$10+I16*Unit_Data!$D$16+W16*Unit_Data!$D$24 -> 399.24 | AH16: =AE16-AF16-AG16 -> 851.244 | AI16: =IF(J16>0,AH16/J16,0) -> 5.67496
... A35: 31 | B35: 46326 | C35: Plan | D35: 40 | E35: 40 | F35: 40 | G35: 30 | H35: 22 | I35: 32 | J35: =SUM(D35:G35) -> 150 | K35: =SUMPRODUCT($D35:$G35,Crude_Data!$C$5:$F$5) -> 3.8 | L35: =SUMPRODUCT($D35:$G35,Crude_Data!$C$6:$F$6) -> 31.6 | M35: =SUMPRODUCT($D35:$G35,Crude_Data!$C$7:$F$7) -> 23.3 | N35: =SUMPRODUCT($D35:$G35,Crude_Data!$C$8:$F$8) -> 38.4 | O35: =SUMPRODUCT($D35:$G35,Crude_Data!$C$9:$F$9) -> 51.4 | P35: =IF(O35>0,SUMPRODUCT($D35:$G35,Crude_Data!$C$9:$F$9,Crude_Data!$C$12:$F$12)/O35,0) -> 1.4610895 | Q35: =H35*Unit_Data!$D$11 -> 18.48 | R35: =H35*Unit_Data!$D$12 -> 1.76 | S35: =I35*Unit_Data!$D$17 -> 16.64 | T35: =I35*Unit_Data!$D$18 -> 5.76 | U35: =I35*Unit_Data!$D$19 -> 5.76 | V35: =I35*Unit_Data!$D$20 -> 1.92 | W35: =N35+U35 -> 44.16 | X35: =K35+R35+T35 -> 11.32 | Y35: =L35-H35 -> 9.6 | Z35: =Q35+S35 -> 35.12 | AA35: =M35 -> 23.3 | AB35: =W35*Unit_Data!$D$25 -> 43.2768 | AC35: =O35-I35+V35 -> 21.32 | AD35: =IF(Z35>0,(Q35*Unit_Data!$D$26+S35*Unit_Data!$D$27)/Z35,0) -> 95.157175 | AE35: =SUMPRODUCT(X35:AC35,Product_Data!$C$4:$H$4) -> 13345.484 | AF35: =SUMPRODUCT(D35:G35,Crude_Data!$C$4:$F$4) -> 12095 | AG35: =J35*Unit_Data!$D$7+H35*Unit_Data!$D$10+I35*Unit_Data!$D$16+W35*Unit_Data!$D$24 -> 399.24 | AH35: =AE35-AF35-AG35 -> 851.244 | AI35: =IF(J35>0,AH35/J35,0) -> 5.67496
A36: Month | C36: Total | D36: =SUM(D5:D35) -> 1231 | E36: =SUM(E5:E35) -> 1222 | F36: =SUM(F5:F35) -> 1236 | G36: =SUM(G5:G35) -> 921 | H36: =SUM(H5:H35) -> 678 | I36: =SUM(I5:I35) -> 987 | J36: =SUM(J5:J35) -> 4610 | K36: =SUM(K5:K35) -> 116.78 | ... O36: =SUM(O5:O35) -> 1579.45 | P36: =AVERAGE(P5:P35) -> 1.4607668 | Q36: =SUM(Q5:Q35) -> 569.52 | R36: =SUM(R5:R35) -> 54.24 | S36: =SUM(S5:S35) -> 513.24 | T36: =SUM(T5:T35) -> 177.66 | U36: =SUM(U5:U35) -> 177.66 | V36: =SUM(V5:V35) -> 59.22 | W36: =SUM(W5:W35) -> 1358.22 | X36: =SUM(X5:X35) -> 348.68 | ... AC36: =SUM(AC5:AC35) -> 651.67 | AD36: =AVERAGE(AD5:AD35) -> 95.155761 | AE36: =SUM(AE5:AE35) -> 410237.03 | AF36: =SUM(AF5:AF35) -> 371733.5 | AG36: =SUM(AG5:AG35) -> 12290.33 | AH36: =SUM(AH5:AH35) -> 26213.198 | AI36: =IF(J36>0,AH36/J36,0) -> 5.6861601
A38: KPIs
A39: Month gross margin ($k) | G39: =AH36 -> 26213.198
A40: Actual-days margin ($k) – locked | G40: =SUMIF(C5:C35,"Actual",AH5:AH35) -> 9188.318
A41: Plan-days margin ($k) – OBJECTIVE | G41: =SUMIF(C5:C35,"Plan",AH5:AH35) -> 17024.88
A42: Total crude run (kbbl) | G42: =J36 -> 4610
A43: Constraint violations (from Constraint_Check) | G43: =Constraint_Check!X37 -> 0
A44: Plan status | G44: =IF(Constraint_Check!X37=0,"FEASIBLE","INFEASIBLE – see Constraint_Check") -> FEASIBLE

Sheet Tank_Balance
A1: Daily Tank Balance (kbbl) – long format, one row per tank per day
A2: Closing = Opening + Inflow − Outflow. Crude: inflow = receipts, outflow = CDU charge. Product: inflow = production, outflow = liftings.
A4: Tank ID | B4: Service | C4: Type | D4: Day | E4: Date | F4: Opening | G4: Inflow | H4: Outflow | I4: Closing | J4: Min heel | K4: Capacity | L4: Status | M4: Fill %
A5: TK-101 | B5: Arab Light | C5: Crude | D5: 1 | E5: =Daily_Plan!B5 -> 46296 | F5: =Tank_Master!$F$4 -> 700 | G5: =Crude_Receipts!C5 -> 0 | H5: =Daily_Plan!D5 -> 40 | I5: =F5+G5-H5 -> 660 | J5: =Tank_Master!$E$4 -> 150 | K5: =Tank_Master!$D$4 -> 1500 | L5: =IF(I5<J5-0.001,"BELOW MIN",IF(I5>K5+0.001,"ABOVE MAX","OK")) -> OK | M5: =IF(K5>0,I5/K5,0) -> 0.44
A6: TK-101 | B6: Arab Light | C6: Crude | D6: 2 | E6: =Daily_Plan!B6 -> 46297 | F6: =I5 -> 660 | G6: =Crude_Receipts!C6 -> 0 | H6: =Daily_Plan!D6 -> 40 | I6: =F6+G6-H6 -> 620 | J6: =Tank_Master!$E$4 -> 150 | K6: =Tank_Master!$D$4 -> 1500 | L6: =IF(I6<J6-0.001,"BELOW MIN",IF(I6>K6+0.001,"ABOVE MAX","OK")) -> OK | M6: =IF(K6>0,I6/K6,0) -> 0.41333333
A7: TK-101 | B7: Arab Light | C7: Crude | D7: 3 | E7: =Daily_Plan!B7 -> 46298 | F7: =I6 -> 620 | G7: =Crude_Receipts!C7 -> 0 | H7: =Daily_Plan!D7 -> 41 | I7: =F7+G7-H7 -> 579 | J7: =Tank_Master!$E$4 -> 150 | K7: =Tank_Master!$D$4 -> 1500 | L7: =IF(I7<J7-0.001,"BELOW MIN",IF(I7>K7+0.001,"ABOVE MAX","OK")) -> OK | M7: =IF(K7>0,I7/K7,0) -> 0.386
A8: TK-101 | B8: Arab Light | C8: Crude | D8: 4 | E8: =Daily_Plan!B8 -> 46299 | F8: =I7 -> 579 | G8: =Crude_Receipts!C8 -> 0 | H8: =Daily_Plan!D8 -> 39 | I8: =F8+G8-H8 -> 540 | J8: =Tank_Master!$E$4 -> 150 | K8: =Tank_Master!$D$4 -> 1500 | L8: =IF(I8<J8-0.001,"BELOW MIN",IF(I8>K8+0.001,"ABOVE MAX","OK")) -> OK | M8: =IF(K8>0,I8/K8,0) -> 0.36
A9: TK-101 | B9: Arab Light | C9: Crude | D9: 5 | E9: =Daily_Plan!B9 -> 46300 | F9: =I8 -> 540 | G9: =Crude_Receipts!C9 -> 0 | H9: =Daily_Plan!D9 -> 35 | I9: =F9+G9-H9 -> 505 | J9: =Tank_Master!$E$4 -> 150 | K9: =Tank_Master!$D$4 -> 1500 | L9: =IF(I9<J9-0.001,"BELOW MIN",IF(I9>K9+0.001,"ABOVE MAX","OK")) -> OK | M9: =IF(K9>0,I9/K9,0) -> 0.33666667
A10: TK-101 | B10: Arab Light | C10: Crude | D10: 6 | E10: =Daily_Plan!B10 -> 46301 | F10: =I9 -> 505 | G10: =Crude_Receipts!C10 -> 0 | H10: =Daily_Plan!D10 -> 37 | I10: =F10+G10-H10 -> 468 | J10: =Tank_Master!$E$4 -> 150 | K10: =Tank_Master!$D$4 -> 1500 | L10: =IF(I10<J10-0.001,"BELOW MIN",IF(I10>K10+0.001,"ABOVE MAX","OK")) -> OK | M10: =IF(K10>0,I10/K10,0) -> 0.312
A11: TK-101 | B11: Arab Light | C11: Crude | D11: 7 | E11: =Daily_Plan!B11 -> 46302 | F11: =I10 -> 468 | G11: =Crude_Receipts!C11 -> 0 | H11: =Daily_Plan!D11 -> 39 | I11: =F11+G11-H11 -> 429 | J11: =Tank_Master!$E$4 -> 150 | K11: =Tank_Master!$D$4 -> 1500 | L11: =IF(I11<J11-0.001,"BELOW MIN",IF(I11>K11+0.001,"ABOVE MAX","OK")) -> OK | M11: =IF(K11>0,I11/K11,0) -> 0.286
A12: TK-101 | B12: Arab Light | C12: Crude | D12: 8 | E12: =Daily_Plan!B12 -> 46303 | F12: =I11 -> 429 | G12: =Crude_Receipts!C12 -> 600 | H12: =Daily_Plan!D12 -> 40 | I12: =F12+G12-H12 -> 989 | J12: =Tank_Master!$E$4 -> 150 | K12: =Tank_Master!$D$4 -> 1500 | L12: =IF(I12<J12-0.001,"BELOW MIN",IF(I12>K12+0.001,"ABOVE MAX","OK")) -> OK | M12: =IF(K12>0,I12/K12,0) -> 0.65933333
A13: TK-101 | B13: Arab Light | C13: Crude | D13: 9 | E13: =Daily_Plan!B13 -> 46304 | F13: =I12 -> 989 | G13: =Crude_Receipts!C13 -> 0 | H13: =Daily_Plan!D13 -> 40 | I13: =F13+G13-H13 -> 949 | J13: =Tank_Master!$E$4 -> 150 | K13: =Tank_Master!$D$4 -> 1500 | L13: =IF(I13<J13-0.001,"BELOW MIN",IF(I13>K13+0.001,"ABOVE MAX","OK")) -> OK | M13: =IF(K13>0,I13/K13,0) -> 0.63266667
A14: TK-101 | B14: Arab Light | C14: Crude | D14: 10 | E14: =Daily_Plan!B14 -> 46305 | F14: =I13 -> 949 | G14: =Crude_Receipts!C14 -> 0 | H14: =Daily_Plan!D14 -> 40 | I14: =F14+G14-H14 -> 909 | J14: =Tank_Master!$E$4 -> 150 | K14: =Tank_Master!$D$4 -> 1500 | L14: =IF(I14<J14-0.001,"BELOW MIN",IF(I14>K14+0.001,"ABOVE MAX","OK")) -> OK | M14: =IF(K14>0,I14/K14,0) -> 0.606
A15: TK-101 | B15: Arab Light | C15: Crude | D15: 11 | E15: =Daily_Plan!B15 -> 46306 | F15: =I14 -> 909 | G15: =Crude_Receipts!C15 -> 0 | H15: =Daily_Plan!D15 -> 40 | I15: =F15+G15-H15 -> 869 | J15: =Tank_Master!$E$4 -> 150 | K15: =Tank_Master!$D$4 -> 1500 | L15: =IF(I15<J15-0.001,"BELOW MIN",IF(I15>K15+0.001,"ABOVE MAX","OK")) -> OK | M15: =IF(K15>0,I15/K15,0) -> 0.57933333
A16: TK-101 | B16: Arab Light | C16: Crude | D16: 12 | E16: =Daily_Plan!B16 -> 46307 | F16: =I15 -> 869 | G16: =Crude_Receipts!C16 -> 0 | H16: =Daily_Plan!D16 -> 40 | I16: =F16+G16-H16 -> 829 | J16: =Tank_Master!$E$4 -> 150 | K16: =Tank_Master!$D$4 -> 1500 | L16: =IF(I16<J16-0.001,"BELOW MIN",IF(I16>K16+0.001,"ABOVE MAX","OK")) -> OK | M16: =IF(K16>0,I16/K16,0) -> 0.55266667
A17: TK-101 | B17: Arab Light | C17: Crude | D17: 13 | E17: =Daily_Plan!B17 -> 46308 | F17: =I16 -> 829 | G17: =Crude_Receipts!C17 -> 0 | H17: =Daily_Plan!D17 -> 40 | I17: =F17+G17-H17 -> 789 | J17: =Tank_Master!$E$4 -> 150 | K17: =Tank_Master!$D$4 -> 1500 | L17: =IF(I17<J17-0.001,"BELOW MIN",IF(I17>K17+0.001,"ABOVE MAX","OK")) -> OK | M17: =IF(K17>0,I17/K17,0) -> 0.526
... A35: TK-101 | B35: Arab Light | C35: Crude | D35: 31 | E35: =Daily_Plan!B35 -> 46326 | F35: =I34 -> 609 | G35: =Crude_Receipts!C35 -> 0 | H35: =Daily_Plan!D35 -> 40 | I35: =F35+G35-H35 -> 569 | J35: =Tank_Master!$E$4 -> 150 | K35: =Tank_Master!$D$4 -> 1500 | L35: =IF(I35<J35-0.001,"BELOW MIN",IF(I35>K35+0.001,"ABOVE MAX","OK")) -> OK | M35: =IF(K35>0,I35/K35,0) -> 0.37933333
A36: TK-102 | B36: Murban | C36: Crude | D36: 1 | E36: =Daily_Plan!B5 -> 46296 | F36: =Tank_Master!$F$5 -> 500 | G36: =Crude_Receipts!D5 -> 0 | H36: =Daily_Plan!E5 -> 40 | I36: =F36+G36-H36 -> 460 | J36: =Tank_Master!$E$5 -> 100 | K36: =Tank_Master!$D$5 -> 1000 | L36: =IF(I36<J36-0.001,"BELOW MIN",IF(I36>K36+0.001,"ABOVE MAX","OK")) -> OK | M36: =IF(K36>0,I36/K36,0) -> 0.46
A37: TK-102 | B37: Murban | C37: Crude | D37: 2 | E37: =Daily_Plan!B6 -> 46297 | F37: =I36 -> 460 | G37: =Crude_Receipts!D6 -> 0 | H37: =Daily_Plan!E6 -> 40 | I37: =F37+G37-H37 -> 420 | J37: =Tank_Master!$E$5 -> 100 | K37: =Tank_Master!$D$5 -> 1000 | L37: =IF(I37<J37-0.001,"BELOW MIN",IF(I37>K37+0.001,"ABOVE MAX","OK")) -> OK | M37: =IF(K37>0,I37/K37,0) -> 0.42
A38: TK-102 | B38: Murban | C38: Crude | D38: 3 | E38: =Daily_Plan!B7 -> 46298 | F38: =I37 -> 420 | G38: =Crude_Receipts!D7 -> 0 | H38: =Daily_Plan!E7 -> 38 | I38: =F38+G38-H38 -> 382 | J38: =Tank_Master!$E$5 -> 100 | K38: =Tank_Master!$D$5 -> 1000 | L38: =IF(I38<J38-0.001,"BELOW MIN",IF(I38>K38+0.001,"ABOVE MAX","OK")) -> OK | M38: =IF(K38>0,I38/K38,0) -> 0.382
A39: TK-102 | B39: Murban | C39: Crude | D39: 4 | E39: =Daily_Plan!B8 -> 46299 | F39: =I38 -> 382 | G39: =Crude_Receipts!D8 -> 0 | H39: =Daily_Plan!E8 -> 36 | I39: =F39+G39-H39 -> 346 | J39: =Tank_Master!$E$5 -> 100 | K39: =Tank_Master!$D$5 -> 1000 | L39: =IF(I39<J39-0.001,"BELOW MIN",IF(I39>K39+0.001,"ABOVE MAX","OK")) -> OK | M39: =IF(K39>0,I39/K39,0) -> 0.346
A40: TK-102 | B40: Murban | C40: Crude | D40: 5 | E40: =Daily_Plan!B9 -> 46300 | F40: =I39 -> 346 | G40: =Crude_Receipts!D9 -> 500 | H40: =Daily_Plan!E9 -> 34 | I40: =F40+G40-H40 -> 812 | J40: =Tank_Master!$E$5 -> 100 | K40: =Tank_Master!$D$5 -> 1000 | L40: =IF(I40<J40-0.001,"BELOW MIN",IF(I40>K40+0.001,"ABOVE MAX","OK")) -> OK | M40: =IF(K40>0,I40/K40,0) -> 0.812
A41: TK-102 | B41: Murban | C41: Crude | D41: 6 | E41: =Daily_Plan!B10 -> 46301 | F41: =I40 -> 812 | G41: =Crude_Receipts!D10 -> 0 | H41: =Daily_Plan!E10 -> 36 | I41: =F41+G41-H41 -> 776 | J41: =Tank_Master!$E$5 -> 100 | K41: =Tank_Master!$D$5 -> 1000 | L41: =IF(I41<J41-0.001,"BELOW MIN",IF(I41>K41+0.001,"ABOVE MAX","OK")) -> OK | M41: =IF(K41>0,I41/K41,0) -> 0.776
A42: TK-102 | B42: Murban | C42: Crude | D42: 7 | E42: =Daily_Plan!B11 -> 46302 | F42: =I41 -> 776 | G42: =Crude_Receipts!D11 -> 0 | H42: =Daily_Plan!E11 -> 38 | I42: =F42+G42-H42 -> 738 | J42: =Tank_Master!$E$5 -> 100 | K42: =Tank_Master!$D$5 -> 1000 | L42: =IF(I42<J42-0.001,"BELOW MIN",IF(I42>K42+0.001,"ABOVE MAX","OK")) -> OK | M42: =IF(K42>0,I42/K42,0) -> 0.738
A43: TK-102 | B43: Murban | C43: Crude | D43: 8 | E43: =Daily_Plan!B12 -> 46303 | F43: =I42 -> 738 | G43: =Crude_Receipts!D12 -> 0 | H43: =Daily_Plan!E12 -> 40 | I43: =F43+G43-H43 -> 698 | J43: =Tank_Master!$E$5 -> 100 | K43: =Tank_Master!$D$5 -> 1000 | L43: =IF(I43<J43-0.001,"BELOW MIN",IF(I43>K43+0.001,"ABOVE MAX","OK")) -> OK | M43: =IF(K43>0,I43/K43,0) -> 0.698
A44: TK-102 | B44: Murban | C44: Crude | D44: 9 | E44: =Daily_Plan!B13 -> 46304 | F44: =I43 -> 698 | G44: =Crude_Receipts!D13 -> 0 | H44: =Daily_Plan!E13 -> 40 | I44: =F44+G44-H44 -> 658 | J44: =Tank_Master!$E$5 -> 100 | K44: =Tank_Master!$D$5 -> 1000 | L44: =IF(I44<J44-0.001,"BELOW MIN",IF(I44>K44+0.001,"ABOVE MAX","OK")) -> OK | M44: =IF(K44>0,I44/K44,0) -> 0.658
A45: TK-102 | B45: Murban | C45: Crude | D45: 10 | E45: =Daily_Plan!B14 -> 46305 | F45: =I44 -> 658 | G45: =Crude_Receipts!D14 -> 0 | H45: =Daily_Plan!E14 -> 40 | I45: =F45+G45-H45 -> 618 | J45: =Tank_Master!$E$5 -> 100 | K45: =Tank_Master!$D$5 -> 1000 | L45: =IF(I45<J45-0.001,"BELOW MIN",IF(I45>K45+0.001,"ABOVE MAX","OK")) -> OK | M45: =IF(K45>0,I45/K45,0) -> 0.618
A46: TK-102 | B46: Murban | C46: Crude | D46: 11 | E46: =Daily_Plan!B15 -> 46306 | F46: =I45 -> 618 | G46: =Crude_Receipts!D15 -> 0 | H46: =Daily_Plan!E15 -> 40 | I46: =F46+G46-H46 -> 578 | J46: =Tank_Master!$E$5 -> 100 | K46: =Tank_Master!$D$5 -> 1000 | L46: =IF(I46<J46-0.001,"BELOW MIN",IF(I46>K46+0.001,"ABOVE MAX","OK")) -> OK | M46: =IF(K46>0,I46/K46,0) -> 0.578
A47: TK-102 | B47: Murban | C47: Crude | D47: 12 | E47: =Daily_Plan!B16 -> 46307 | F47: =I46 -> 578 | G47: =Crude_Receipts!D16 -> 0 | H47: =Daily_Plan!E16 -> 40 | I47: =F47+G47-H47 -> 538 | J47: =Tank_Master!$E$5 -> 100 | K47: =Tank_Master!$D$5 -> 1000 | L47: =IF(I47<J47-0.001,"BELOW MIN",IF(I47>K47+0.001,"ABOVE MAX","OK")) -> OK | M47: =IF(K47>0,I47/K47,0) -> 0.538
A48: TK-102 | B48: Murban | C48: Crude | D48: 13 | E48: =Daily_Plan!B17 -> 46308 | F48: =I47 -> 538 | G48: =Crude_Receipts!D17 -> 0 | H48: =Daily_Plan!E17 -> 40 | I48: =F48+G48-H48 -> 498 | J48: =Tank_Master!$E$5 -> 100 | K48: =Tank_Master!$D$5 -> 1000 | L48: =IF(I48<J48-0.001,"BELOW MIN",IF(I48>K48+0.001,"ABOVE MAX","OK")) -> OK | M48: =IF(K48>0,I48/K48,0) -> 0.498
... A66: TK-102 | B66: Murban | C66: Crude | D66: 31 | E66: =Daily_Plan!B35 -> 46326 | F66: =I65 -> 318 | G66: =Crude_Receipts!D35 -> 0 | H66: =Daily_Plan!E35 -> 40 | I66: =F66+G66-H66 -> 278 | J66: =Tank_Master!$E$5 -> 100 | K66: =Tank_Master!$D$5 -> 1000 | L66: =IF(I66<J66-0.001,"BELOW MIN",IF(I66>K66+0.001,"ABOVE MAX","OK")) -> OK | M66: =IF(K66>0,I66/K66,0) -> 0.278
A67: TK-103 | B67: Tapis | C67: Crude | D67: 1 | E67: =Daily_Plan!B5 -> 46296 | F67: =Tank_Master!$F$6 -> 450 | G67: =Crude_Receipts!E5 -> 0 | H67: =Daily_Plan!F5 -> 40 | I67: =F67+G67-H67 -> 410 | J67: =Tank_Master!$E$6 -> 90 | K67: =Tank_Master!$D$6 -> 900 | L67: =IF(I67<J67-0.001,"BELOW MIN",IF(I67>K67+0.001,"ABOVE MAX","OK")) -> OK | M67: =IF(K67>0,I67/K67,0) -> 0.45555556
A68: TK-103 | B68: Tapis | C68: Crude | D68: 2 | E68: =Daily_Plan!B6 -> 46297 | F68: =I67 -> 410 | G68: =Crude_Receipts!E6 -> 0 | H68: =Daily_Plan!F6 -> 40 | I68: =F68+G68-H68 -> 370 | J68: =Tank_Master!$E$6 -> 90 | K68: =Tank_Master!$D$6 -> 900 | L68: =IF(I68<J68-0.001,"BELOW MIN",IF(I68>K68+0.001,"ABOVE MAX","OK")) -> OK | M68: =IF(K68>0,I68/K68,0) -> 0.41111111
A69: TK-103 | B69: Tapis | C69: Crude | D69: 3 | E69: =Daily_Plan!B7 -> 46298 | F69: =I68 -> 370 | G69: =Crude_Receipts!E7 -> 0 | H69: =Daily_Plan!F7 -> 41 | I69: =F69+G69-H69 -> 329 | J69: =Tank_Master!$E$6 -> 90 | K69: =Tank_Master!$D$6 -> 900 | L69: =IF(I69<J69-0.001,"BELOW MIN",IF(I69>K69+0.001,"ABOVE MAX","OK")) -> OK | M69: =IF(K69>0,I69/K69,0) -> 0.36555556
A70: TK-103 | B70: Tapis | C70: Crude | D70: 4 | E70: =Daily_Plan!B8 -> 46299 | F70: =I69 -> 329 | G70: =Crude_Receipts!E8 -> 0 | H70: =Daily_Plan!F8 -> 39 | I70: =F70+G70-H70 -> 290 | J70: =Tank_Master!$E$6 -> 90 | K70: =Tank_Master!$D$6 -> 900 | L70: =IF(I70<J70-0.001,"BELOW MIN",IF(I70>K70+0.001,"ABOVE MAX","OK")) -> OK | M70: =IF(K70>0,I70/K70,0) -> 0.32222222
A71: TK-103 | B71: Tapis | C71: Crude | D71: 5 | E71: =Daily_Plan!B9 -> 46300 | F71: =I70 -> 290 | G71: =Crude_Receipts!E9 -> 0 | H71: =Daily_Plan!F9 -> 37 | I71: =F71+G71-H71 -> 253 | J71: =Tank_Master!$E$6 -> 90 | K71: =Tank_Master!$D$6 -> 900 | L71: =IF(I71<J71-0.001,"BELOW MIN",IF(I71>K71+0.001,"ABOVE MAX","OK")) -> OK | M71: =IF(K71>0,I71/K71,0) -> 0.28111111
A72: TK-103 | B72: Tapis | C72: Crude | D72: 6 | E72: =Daily_Plan!B10 -> 46301 | F72: =I71 -> 253 | G72: =Crude_Receipts!E10 -> 400 | H72: =Daily_Plan!F10 -> 38 | I72: =F72+G72-H72 -> 615 | J72: =Tank_Master!$E$6 -> 90 | K72: =Tank_Master!$D$6 -> 900 | L72: =IF(I72<J72-0.001,"BELOW MIN",IF(I72>K72+0.001,"ABOVE MAX","OK")) -> OK | M72: =IF(K72>0,I72/K72,0) -> 0.68333333
A73: TK-103 | B73: Tapis | C73: Crude | D73: 7 | E73: =Daily_Plan!B11 -> 46302 | F73: =I72 -> 615 | G73: =Crude_Receipts!E11 -> 0 | H73: =Daily_Plan!F11 -> 40 | I73: =F73+G73-H73 -> 575 | J73: =Tank_Master!$E$6 -> 90 | K73: =Tank_Master!$D$6 -> 900 | L73: =IF(I73<J73-0.001,"BELOW MIN",IF(I73>K73+0.001,"ABOVE MAX","OK")) -> OK | M73: =IF(K73>0,I73/K73,0) -> 0.63888889
A74: TK-103 | B74: Tapis | C74: Crude | D74: 8 | E74: =Daily_Plan!B12 -> 46303 | F74: =I73 -> 575 | G74: =Crude_Receipts!E12 -> 0 | H74: =Daily_Plan!F12 -> 40 | I74: =F74+G74-H74 -> 535 | J74: =Tank_Master!$E$6 -> 90 | K74: =Tank_Master!$D$6 -> 900 | L74: =IF(I74<J74-0.001,"BELOW MIN",IF(I74>K74+0.001,"ABOVE MAX","OK")) -> OK | M74: =IF(K74>0,I74/K74,0) -> 0.59444444
A75: TK-103 | B75: Tapis | C75: Crude | D75: 9 | E75: =Daily_Plan!B13 -> 46304 | F75: =I74 -> 535 | G75: =Crude_Receipts!E13 -> 0 | H75: =Daily_Plan!F13 -> 41 | I75: =F75+G75-H75 -> 494 | J75: =Tank_Master!$E$6 -> 90 | K75: =Tank_Master!$D$6 -> 900 | L75: =IF(I75<J75-0.001,"BELOW MIN",IF(I75>K75+0.001,"ABOVE MAX","OK")) -> OK | M75: =IF(K75>0,I75/K75,0) -> 0.54888889
A76: TK-103 | B76: Tapis | C76: Crude | D76: 10 | E76: =Daily_Plan!B14 -> 46305 | F76: =I75 -> 494 | G76: =Crude_Receipts!E14 -> 0 | H76: =Daily_Plan!F14 -> 40 | I76: =F76+G76-H76 -> 454 | J76: =Tank_Master!$E$6 -> 90 | K76: =Tank_Master!$D$6 -> 900 | L76: =IF(I76<J76-0.001,"BELOW MIN",IF(I76>K76+0.001,"ABOVE MAX","OK")) -> OK | M76: =IF(K76>0,I76/K76,0) -> 0.50444444
A77: TK-103 | B77: Tapis | C77: Crude | D77: 11 | E77: =Daily_Plan!B15 -> 46306 | F77: =I76 -> 454 | G77: =Crude_Receipts!E15 -> 0 | H77: =Daily_Plan!F15 -> 40 | I77: =F77+G77-H77 -> 414 | J77: =Tank_Master!$E$6 -> 90 | K77: =Tank_Master!$D$6 -> 900 | L77: =IF(I77<J77-0.001,"BELOW MIN",IF(I77>K77+0.001,"ABOVE MAX","OK")) -> OK | M77: =IF(K77>0,I77/K77,0) -> 0.46
A78: TK-103 | B78: Tapis | C78: Crude | D78: 12 | E78: =Daily_Plan!B16 -> 46307 | F78: =I77 -> 414 | G78: =Crude_Receipts!E16 -> 0 | H78: =Daily_Plan!F16 -> 40 | I78: =F78+G78-H78 -> 374 | J78: =Tank_Master!$E$6 -> 90 | K78: =Tank_Master!$D$6 -> 900 | L78: =IF(I78<J78-0.001,"BELOW MIN",IF(I78>K78+0.001,"ABOVE MAX","OK")) -> OK | M78: =IF(K78>0,I78/K78,0) -> 0.41555556
A79: TK-103 | B79: Tapis | C79: Crude | D79: 13 | E79: =Daily_Plan!B17 -> 46308 | F79: =I78 -> 374 | G79: =Crude_Receipts!E17 -> 0 | H79: =Daily_Plan!F17 -> 40 | I79: =F79+G79-H79 -> 334 | J79: =Tank_Master!$E$6 -> 90 | K79: =Tank_Master!$D$6 -> 900 | L79: =IF(I79<J79-0.001,"BELOW MIN",IF(I79>K79+0.001,"ABOVE MAX","OK")) -> OK | M79: =IF(K79>0,I79/K79,0) -> 0.37111111
... A97: TK-103 | B97: Tapis | C97: Crude | D97: 31 | E97: =Daily_Plan!B35 -> 46326 | F97: =I96 -> 454 | G97: =Crude_Receipts!E35 -> 0 | H97: =Daily_Plan!F35 -> 40 | I97: =F97+G97-H97 -> 414 | J97: =Tank_Master!$E$6 -> 90 | K97: =Tank_Master!$D$6 -> 900 | L97: =IF(I97<J97-0.001,"BELOW MIN",IF(I97>K97+0.001,"ABOVE MAX","OK")) -> OK | M97: =IF(K97>0,I97/K97,0) -> 0.46
A98: TK-104 | B98: Kimanis | C98: Crude | D98: 1 | E98: =Daily_Plan!B5 -> 46296 | F98: =Tank_Master!$F$7 -> 380 | G98: =Crude_Receipts!F5 -> 0 | H98: =Daily_Plan!G5 -> 30 | I98: =F98+G98-H98 -> 350 | J98: =Tank_Master!$E$7 -> 80 | K98: =Tank_Master!$D$7 -> 800 | L98: =IF(I98<J98-0.001,"BELOW MIN",IF(I98>K98+0.001,"ABOVE MAX","OK")) -> OK | M98: =IF(K98>0,I98/K98,0) -> 0.4375
A99: TK-104 | B99: Kimanis | C99: Crude | D99: 2 | E99: =Daily_Plan!B6 -> 46297 | F99: =I98 -> 350 | G99: =Crude_Receipts!F6 -> 0 | H99: =Daily_Plan!G6 -> 30 | I99: =F99+G99-H99 -> 320 | J99: =Tank_Master!$E$7 -> 80 | K99: =Tank_Master!$D$7 -> 800 | L99: =IF(I99<J99-0.001,"BELOW MIN",IF(I99>K99+0.001,"ABOVE MAX","OK")) -> OK | M99: =IF(K99>0,I99/K99,0) -> 0.4
A100: TK-104 | B100: Kimanis | C100: Crude | D100: 3 | E100: =Daily_Plan!B7 -> 46298 | F100: =I99 -> 320 | G100: =Crude_Receipts!F7 -> 0 | H100: =Daily_Plan!G7 -> 30 | I100: =F100+G100-H100 -> 290 | J100: =Tank_Master!$E$7 -> 80 | K100: =Tank_Master!$D$7 -> 800 | L100: =IF(I100<J100-0.001,"BELOW MIN",IF(I100>K100+0.001,"ABOVE MAX","OK")) -> OK | M100: =IF(K100>0,I100/K100,0) -> 0.3625
A101: TK-104 | B101: Kimanis | C101: Crude | D101: 4 | E101: =Daily_Plan!B8 -> 46299 | F101: =I100 -> 290 | G101: =Crude_Receipts!F8 -> 0 | H101: =Daily_Plan!G8 -> 28 | I101: =F101+G101-H101 -> 262 | J101: =Tank_Master!$E$7 -> 80 | K101: =Tank_Master!$D$7 -> 800 | L101: =IF(I101<J101-0.001,"BELOW MIN",IF(I101>K101+0.001,"ABOVE MAX","OK")) -> OK | M101: =IF(K101>0,I101/K101,0) -> 0.3275
A102: TK-104 | B102: Kimanis | C102: Crude | D102: 5 | E102: =Daily_Plan!B9 -> 46300 | F102: =I101 -> 262 | G102: =Crude_Receipts!F9 -> 0 | H102: =Daily_Plan!G9 -> 26 | I102: =F102+G102-H102 -> 236 | J102: =Tank_Master!$E$7 -> 80 | K102: =Tank_Master!$D$7 -> 800 | L102: =IF(I102<J102-0.001,"BELOW MIN",IF(I102>K102+0.001,"ABOVE MAX","OK")) -> OK | M102: =IF(K102>0,I102/K102,0) -> 0.295
A103: TK-104 | B103: Kimanis | C103: Crude | D103: 6 | E103: =Daily_Plan!B10 -> 46301 | F103: =I102 -> 236 | G103: =Crude_Receipts!F10 -> 0 | H103: =Daily_Plan!G10 -> 28 | I103: =F103+G103-H103 -> 208 | J103: =Tank_Master!$E$7 -> 80 | K103: =Tank_Master!$D$7 -> 800 | L103: =IF(I103<J103-0.001,"BELOW MIN",IF(I103>K103+0.001,"ABOVE MAX","OK")) -> OK | M103: =IF(K103>0,I103/K103,0) -> 0.26
A104: TK-104 | B104: Kimanis | C104: Crude | D104: 7 | E104: =Daily_Plan!B11 -> 46302 | F104: =I103 -> 208 | G104: =Crude_Receipts!F11 -> 0 | H104: =Daily_Plan!G11 -> 30 | I104: =F104+G104-H104 -> 178 | J104: =Tank_Master!$E$7 -> 80 | K104: =Tank_Master!$D$7 -> 800 | L104: =IF(I104<J104-0.001,"BELOW MIN",IF(I104>K104+0.001,"ABOVE MAX","OK")) -> OK | M104: =IF(K104>0,I104/K104,0) -> 0.2225
A105: TK-104 | B105: Kimanis | C105: Crude | D105: 8 | E105: =Daily_Plan!B12 -> 46303 | F105: =I104 -> 178 | G105: =Crude_Receipts!F12 -> 0 | H105: =Daily_Plan!G12 -> 30 | I105: =F105+G105-H105 -> 148 | J105: =Tank_Master!$E$7 -> 80 | K105: =Tank_Master!$D$7 -> 800 | L105: =IF(I105<J105-0.001,"BELOW MIN",IF(I105>K105+0.001,"ABOVE MAX","OK")) -> OK | M105: =IF(K105>0,I105/K105,0) -> 0.185
A106: TK-104 | B106: Kimanis | C106: Crude | D106: 9 | E106: =Daily_Plan!B13 -> 46304 | F106: =I105 -> 148 | G106: =Crude_Receipts!F13 -> 0 | H106: =Daily_Plan!G13 -> 29 | I106: =F106+G106-H106 -> 119 | J106: =Tank_Master!$E$7 -> 80 | K106: =Tank_Master!$D$7 -> 800 | L106: =IF(I106<J106-0.001,"BELOW MIN",IF(I106>K106+0.001,"ABOVE MAX","OK")) -> OK | M106: =IF(K106>0,I106/K106,0) -> 0.14875
A107: TK-104 | B107: Kimanis | C107: Crude | D107: 10 | E107: =Daily_Plan!B14 -> 46305 | F107: =I106 -> 119 | G107: =Crude_Receipts!F14 -> 350 | H107: =Daily_Plan!G14 -> 30 | I107: =F107+G107-H107 -> 439 | J107: =Tank_Master!$E$7 -> 80 | K107: =Tank_Master!$D$7 -> 800 | L107: =IF(I107<J107-0.001,"BELOW MIN",IF(I107>K107+0.001,"ABOVE MAX","OK")) -> OK | M107: =IF(K107>0,I107/K107,0) -> 0.54875
A108: TK-104 | B108: Kimanis | C108: Crude | D108: 11 | E108: =Daily_Plan!B15 -> 46306 | F108: =I107 -> 439 | G108: =Crude_Receipts!F15 -> 0 | H108: =Daily_Plan!G15 -> 30 | I108: =F108+G108-H108 -> 409 | J108: =Tank_Master!$E$7 -> 80 | K108: =Tank_Master!$D$7 -> 800 | L108: =IF(I108<J108-0.001,"BELOW MIN",IF(I108>K108+0.001,"ABOVE MAX","OK")) -> OK | M108: =IF(K108>0,I108/K108,0) -> 0.51125
A109: TK-104 | B109: Kimanis | C109: Crude | D109: 12 | E109: =Daily_Plan!B16 -> 46307 | F109: =I108 -> 409 | G109: =Crude_Receipts!F16 -> 0 | H109: =Daily_Plan!G16 -> 30 | I109: =F109+G109-H109 -> 379 | J109: =Tank_Master!$E$7 -> 80 | K109: =Tank_Master!$D$7 -> 800 | L109: =IF(I109<J109-0.001,"BELOW MIN",IF(I109>K109+0.001,"ABOVE MAX","OK")) -> OK | M109: =IF(K109>0,I109/K109,0) -> 0.47375
A110: TK-104 | B110: Kimanis | C110: Crude | D110: 13 | E110: =Daily_Plan!B17 -> 46308 | F110: =I109 -> 379 | G110: =Crude_Receipts!F17 -> 0 | H110: =Daily_Plan!G17 -> 30 | I110: =F110+G110-H110 -> 349 | J110: =Tank_Master!$E$7 -> 80 | K110: =Tank_Master!$D$7 -> 800 | L110: =IF(I110<J110-0.001,"BELOW MIN",IF(I110>K110+0.001,"ABOVE MAX","OK")) -> OK | M110: =IF(K110>0,I110/K110,0) -> 0.43625
... A128: TK-104 | B128: Kimanis | C128: Crude | D128: 31 | E128: =Daily_Plan!B35 -> 46326 | F128: =I127 -> 189 | G128: =Crude_Receipts!F35 -> 0 | H128: =Daily_Plan!G35 -> 30 | I128: =F128+G128-H128 -> 159 | J128: =Tank_Master!$E$7 -> 80 | K128: =Tank_Master!$D$7 -> 800 | L128: =IF(I128<J128-0.001,"BELOW MIN",IF(I128>K128+0.001,"ABOVE MAX","OK")) -> OK | M128: =IF(K128>0,I128/K128,0) -> 0.19875
A129: TK-201 | B129: LPG | C129: Product | D129: 1 | E129: =Daily_Plan!B5 -> 46296 | F129: =Tank_Master!$F$8 -> 30 | G129: =Daily_Plan!X5 -> 11.32 | H129: =Product_Liftings!C5 -> 9 | I129: =F129+G129-H129 -> 32.32 | J129: =Tank_Master!$E$8 -> 6 | K129: =Tank_Master!$D$8 -> 60 | L129: =IF(I129<J129-0.001,"BELOW MIN",IF(I129>K129+0.001,"ABOVE MAX","OK")) -> OK | M129: =IF(K129>0,I129/K129,0) -> 0.53866667
A130: TK-201 | B130: LPG | C130: Product | D130: 2 | E130: =Daily_Plan!B6 -> 46297 | F130: =I129 -> 32.32 | G130: =Daily_Plan!X6 -> 11.32 | H130: =Product_Liftings!C6 -> 9 | I130: =F130+G130-H130 -> 34.64 | J130: =Tank_Master!$E$8 -> 6 | K130: =Tank_Master!$D$8 -> 60 | L130: =IF(I130<J130-0.001,"BELOW MIN",IF(I130>K130+0.001,"ABOVE MAX","OK")) -> OK | M130: =IF(K130>0,I130/K130,0) -> 0.57733333
A131: TK-201 | B131: LPG | C131: Product | D131: 3 | E131: =Daily_Plan!B7 -> 46298 | F131: =I130 -> 34.64 | G131: =Daily_Plan!X7 -> 11.57 | H131: =Product_Liftings!C7 -> 9 | I131: =F131+G131-H131 -> 37.21 | J131: =Tank_Master!$E$8 -> 6 | K131: =Tank_Master!$D$8 -> 60 | L131: =IF(I131<J131-0.001,"BELOW MIN",IF(I131>K131+0.001,"ABOVE MAX","OK")) -> OK | M131: =IF(K131>0,I131/K131,0) -> 0.62016667
A132: TK-201 | B132: LPG | C132: Product | D132: 4 | E132: =Daily_Plan!B8 -> 46299 | F132: =I131 -> 37.21 | G132: =Daily_Plan!X8 -> 10.67 | H132: =Product_Liftings!C8 -> 9 | I132: =F132+G132-H132 -> 38.88 | J132: =Tank_Master!$E$8 -> 6 | K132: =Tank_Master!$D$8 -> 60 | L132: =IF(I132<J132-0.001,"BELOW MIN",IF(I132>K132+0.001,"ABOVE MAX","OK")) -> OK | M132: =IF(K132>0,I132/K132,0) -> 0.648
A133: TK-201 | B133: LPG | C133: Product | D133: 5 | E133: =Daily_Plan!B9 -> 46300 | F133: =I132 -> 38.88 | G133: =Daily_Plan!X9 -> 9.91 | H133: =Product_Liftings!C9 -> 9 | I133: =F133+G133-H133 -> 39.79 | J133: =Tank_Master!$E$8 -> 6 | K133: =Tank_Master!$D$8 -> 60 | L133: =IF(I133<J133-0.001,"BELOW MIN",IF(I133>K133+0.001,"ABOVE MAX","OK")) -> OK | M133: =IF(K133>0,I133/K133,0) -> 0.66316667
A134: TK-201 | B134: LPG | C134: Product | D134: 6 | E134: =Daily_Plan!B10 -> 46301 | F134: =I133 -> 39.79 | G134: =Daily_Plan!X10 -> 10.52 | H134: =Product_Liftings!C10 -> 9 | I134: =F134+G134-H134 -> 41.31 | J134: =Tank_Master!$E$8 -> 6 | K134: =Tank_Master!$D$8 -> 60 | L134: =IF(I134<J134-0.001,"BELOW MIN",IF(I134>K134+0.001,"ABOVE MAX","OK")) -> OK | M134: =IF(K134>0,I134/K134,0) -> 0.6885
A135: TK-201 | B135: LPG | C135: Product | D135: 7 | E135: =Daily_Plan!B11 -> 46302 | F135: =I134 -> 41.31 | G135: =Daily_Plan!X11 -> 11.24 | H135: =Product_Liftings!C11 -> 9 | I135: =F135+G135-H135 -> 43.55 | J135: =Tank_Master!$E$8 -> 6 | K135: =Tank_Master!$D$8 -> 60 | L135: =IF(I135<J135-0.001,"BELOW MIN",IF(I135>K135+0.001,"ABOVE MAX","OK")) -> OK | M135: =IF(K135>0,I135/K135,0) -> 0.72583333
A136: TK-201 | B136: LPG | C136: Product | D136: 8 | E136: =Daily_Plan!B12 -> 46303 | F136: =I135 -> 43.55 | G136: =Daily_Plan!X12 -> 11.5 | H136: =Product_Liftings!C12 -> 9 | I136: =F136+G136-H136 -> 46.05 | J136: =Tank_Master!$E$8 -> 6 | K136: =Tank_Master!$D$8 -> 60 | L136: =IF(I136<J136-0.001,"BELOW MIN",IF(I136>K136+0.001,"ABOVE MAX","OK")) -> OK | M136: =IF(K136>0,I136/K136,0) -> 0.7675
A137: TK-201 | B137: LPG | C137: Product | D137: 9 | E137: =Daily_Plan!B13 -> 46304 | F137: =I136 -> 46.05 | G137: =Daily_Plan!X13 -> 11.59 | H137: =Product_Liftings!C13 -> 9 | I137: =F137+G137-H137 -> 48.64 | J137: =Tank_Master!$E$8 -> 6 | K137: =Tank_Master!$D$8 -> 60 | L137: =IF(I137<J137-0.001,"BELOW MIN",IF(I137>K137+0.001,"ABOVE MAX","OK")) -> OK | M137: =IF(K137>0,I137/K137,0) -> 0.81066667
A138: TK-201 | B138: LPG | C138: Product | D138: 10 | E138: =Daily_Plan!B14 -> 46305 | F138: =I137 -> 48.64 | G138: =Daily_Plan!X14 -> 11.32 | H138: =Product_Liftings!C14 -> 39 | I138: =F138+G138-H138 -> 20.96 | J138: =Tank_Master!$E$8 -> 6 | K138: =Tank_Master!$D$8 -> 60 | L138: =IF(I138<J138-0.001,"BELOW MIN",IF(I138>K138+0.001,"ABOVE MAX","OK")) -> OK | M138: =IF(K138>0,I138/K138,0) -> 0.34933333
A139: TK-201 | B139: LPG | C139: Product | D139: 11 | E139: =Daily_Plan!B15 -> 46306 | F139: =I138 -> 20.96 | G139: =Daily_Plan!X15 -> 11.32 | H139: =Product_Liftings!C15 -> 9 | I139: =F139+G139-H139 -> 23.28 | J139: =Tank_Master!$E$8 -> 6 | K139: =Tank_Master!$D$8 -> 60 | L139: =IF(I139<J139-0.001,"BELOW MIN",IF(I139>K139+0.001,"ABOVE MAX","OK")) -> OK | M139: =IF(K139>0,I139/K139,0) -> 0.388
A140: TK-201 | B140: LPG | C140: Product | D140: 12 | E140: =Daily_Plan!B16 -> 46307 | F140: =I139 -> 23.28 | G140: =Daily_Plan!X16 -> 11.32 | H140: =Product_Liftings!C16 -> 9 | I140: =F140+G140-H140 -> 25.6 | J140: =Tank_Master!$E$8 -> 6 | K140: =Tank_Master!$D$8 -> 60 | L140: =IF(I140<J140-0.001,"BELOW MIN",IF(I140>K140+0.001,"ABOVE MAX","OK")) -> OK | M140: =IF(K140>0,I140/K140,0) -> 0.42666667
A141: TK-201 | B141: LPG | C141: Product | D141: 13 | E141: =Daily_Plan!B17 -> 46308 | F141: =I140 -> 25.6 | G141: =Daily_Plan!X17 -> 11.32 | H141: =Product_Liftings!C17 -> 9 | I141: =F141+G141-H141 -> 27.92 | J141: =Tank_Master!$E$8 -> 6 | K141: =Tank_Master!$D$8 -> 60 | L141: =IF(I141<J141-0.001,"BELOW MIN",IF(I141>K141+0.001,"ABOVE MAX","OK")) -> OK | M141: =IF(K141>0,I141/K141,0) -> 0.46533333
... A159: TK-201 | B159: LPG | C159: Product | D159: 31 | E159: =Daily_Plan!B35 -> 46326 | F159: =I158 -> 37.36 | G159: =Daily_Plan!X35 -> 11.32 | H159: =Product_Liftings!C35 -> 9 | I159: =F159+G159-H159 -> 39.68 | J159: =Tank_Master!$E$8 -> 6 | K159: =Tank_Master!$D$8 -> 60 | L159: =IF(I159<J159-0.001,"BELOW MIN",IF(I159>K159+0.001,"ABOVE MAX","OK")) -> OK | M159: =IF(K159>0,I159/K159,0) -> 0.66133333
A160: TK-301 | B160: Naphtha | C160: Product | D160: 1 | E160: =Daily_Plan!B5 -> 46296 | F160: =Tank_Master!$F$9 -> 110 | G160: =Daily_Plan!Y5 -> 9.6 | H160: =Product_Liftings!D5 -> 0 | I160: =F160+G160-H160 -> 119.6 | J160: =Tank_Master!$E$9 -> 25 | K160: =Tank_Master!$D$9 -> 250 | L160: =IF(I160<J160-0.001,"BELOW MIN",IF(I160>K160+0.001,"ABOVE MAX","OK")) -> OK | M160: =IF(K160>0,I160/K160,0) -> 0.4784
A161: TK-301 | B161: Naphtha | C161: Product | D161: 2 | E161: =Daily_Plan!B6 -> 46297 | F161: =I160 -> 119.6 | G161: =Daily_Plan!Y6 -> 9.6 | H161: =Product_Liftings!D6 -> 0 | I161: =F161+G161-H161 -> 129.2 | J161: =Tank_Master!$E$9 -> 25 | K161: =Tank_Master!$D$9 -> 250 | L161: =IF(I161<J161-0.001,"BELOW MIN",IF(I161>K161+0.001,"ABOVE MAX","OK")) -> OK | M161: =IF(K161>0,I161/K161,0) -> 0.5168
A162: TK-301 | B162: Naphtha | C162: Product | D162: 3 | E162: =Daily_Plan!B7 -> 46298 | F162: =I161 -> 129.2 | G162: =Daily_Plan!Y7 -> 8.52 | H162: =Product_Liftings!D7 -> 0 | I162: =F162+G162-H162 -> 137.72 | J162: =Tank_Master!$E$9 -> 25 | K162: =Tank_Master!$D$9 -> 250 | L162: =IF(I162<J162-0.001,"BELOW MIN",IF(I162>K162+0.001,"ABOVE MAX","OK")) -> OK | M162: =IF(K162>0,I162/K162,0) -> 0.55088
A163: TK-301 | B163: Naphtha | C163: Product | D163: 4 | E163: =Daily_Plan!B8 -> 46299 | F163: =I162 -> 137.72 | G163: =Daily_Plan!Y8 -> 8.84 | H163: =Product_Liftings!D8 -> 0 | I163: =F163+G163-H163 -> 146.56 | J163: =Tank_Master!$E$9 -> 25 | K163: =Tank_Master!$D$9 -> 250 | L163: =IF(I163<J163-0.001,"BELOW MIN",IF(I163>K163+0.001,"ABOVE MAX","OK")) -> OK | M163: =IF(K163>0,I163/K163,0) -> 0.58624
A164: TK-301 | B164: Naphtha | C164: Product | D164: 5 | E164: =Daily_Plan!B9 -> 46300 | F164: =I163 -> 146.56 | G164: =Daily_Plan!Y9 -> 8.8 | H164: =Product_Liftings!D9 -> 0 | I164: =F164+G164-H164 -> 155.36 | J164: =Tank_Master!$E$9 -> 25 | K164: =Tank_Master!$D$9 -> 250 | L164: =IF(I164<J164-0.001,"BELOW MIN",IF(I164>K164+0.001,"ABOVE MAX","OK")) -> OK | M164: =IF(K164>0,I164/K164,0) -> 0.62144
A165: TK-301 | B165: Naphtha | C165: Product | D165: 6 | E165: =Daily_Plan!B10 -> 46301 | F165: =I164 -> 155.36 | G165: =Daily_Plan!Y10 -> 9.26 | H165: =Product_Liftings!D10 -> 0 | I165: =F165+G165-H165 -> 164.62 | J165: =Tank_Master!$E$9 -> 25 | K165: =Tank_Master!$D$9 -> 250 | L165: =IF(I165<J165-0.001,"BELOW MIN",IF(I165>K165+0.001,"ABOVE MAX","OK")) -> OK | M165: =IF(K165>0,I165/K165,0) -> 0.65848
A166: TK-301 | B166: Naphtha | C166: Product | D166: 7 | E166: =Daily_Plan!B11 -> 46302 | F166: =I165 -> 164.62 | G166: =Daily_Plan!Y11 -> 8.94 | H166: =Product_Liftings!D11 -> 0 | I166: =F166+G166-H166 -> 173.56 | J166: =Tank_Master!$E$9 -> 25 | K166: =Tank_Master!$D$9 -> 250 | L166: =IF(I166<J166-0.001,"BELOW MIN",IF(I166>K166+0.001,"ABOVE MAX","OK")) -> OK | M166: =IF(K166>0,I166/K166,0) -> 0.69424
A167: TK-301 | B167: Naphtha | C167: Product | D167: 8 | E167: =Daily_Plan!B12 -> 46303 | F167: =I166 -> 173.56 | G167: =Daily_Plan!Y12 -> 9.6 | H167: =Product_Liftings!D12 -> 0 | I167: =F167+G167-H167 -> 183.16 | J167: =Tank_Master!$E$9 -> 25 | K167: =Tank_Master!$D$9 -> 250 | L167: =IF(I167<J167-0.001,"BELOW MIN",IF(I167>K167+0.001,"ABOVE MAX","OK")) -> OK | M167: =IF(K167>0,I167/K167,0) -> 0.73264
A168: TK-301 | B168: Naphtha | C168: Product | D168: 9 | E168: =Daily_Plan!B13 -> 46304 | F168: =I167 -> 183.16 | G168: =Daily_Plan!Y13 -> 8.62 | H168: =Product_Liftings!D13 -> 100 | I168: =F168+G168-H168 -> 91.78 | J168: =Tank_Master!$E$9 -> 25 | K168: =Tank_Master!$D$9 -> 250 | L168: =IF(I168<J168-0.001,"BELOW MIN",IF(I168>K168+0.001,"ABOVE MAX","OK")) -> OK | M168: =IF(K168>0,I168/K168,0) -> 0.36712
A169: TK-301 | B169: Naphtha | C169: Product | D169: 10 | E169: =Daily_Plan!B14 -> 46305 | F169: =I168 -> 91.78 | G169: =Daily_Plan!Y14 -> 9.6 | H169: =Product_Liftings!D14 -> 0 | I169: =F169+G169-H169 -> 101.38 | J169: =Tank_Master!$E$9 -> 25 | K169: =Tank_Master!$D$9 -> 250 | L169: =IF(I169<J169-0.001,"BELOW MIN",IF(I169>K169+0.001,"ABOVE MAX","OK")) -> OK | M169: =IF(K169>0,I169/K169,0) -> 0.40552
A170: TK-301 | B170: Naphtha | C170: Product | D170: 11 | E170: =Daily_Plan!B15 -> 46306 | F170: =I169 -> 101.38 | G170: =Daily_Plan!Y15 -> 9.6 | H170: =Product_Liftings!D15 -> 0 | I170: =F170+G170-H170 -> 110.98 | J170: =Tank_Master!$E$9 -> 25 | K170: =Tank_Master!$D$9 -> 250 | L170: =IF(I170<J170-0.001,"BELOW MIN",IF(I170>K170+0.001,"ABOVE MAX","OK")) -> OK | M170: =IF(K170>0,I170/K170,0) -> 0.44392
A171: TK-301 | B171: Naphtha | C171: Product | D171: 12 | E171: =Daily_Plan!B16 -> 46307 | F171: =I170 -> 110.98 | G171: =Daily_Plan!Y16 -> 9.6 | H171: =Product_Liftings!D16 -> 0 | I171: =F171+G171-H171 -> 120.58 | J171: =Tank_Master!$E$9 -> 25 | K171: =Tank_Master!$D$9 -> 250 | L171: =IF(I171<J171-0.001,"BELOW MIN",IF(I171>K171+0.001,"ABOVE MAX","OK")) -> OK | M171: =IF(K171>0,I171/K171,0) -> 0.48232
A172: TK-301 | B172: Naphtha | C172: Product | D172: 13 | E172: =Daily_Plan!B17 -> 46308 | F172: =I171 -> 120.58 | G172: =Daily_Plan!Y17 -> 9.6 | H172: =Product_Liftings!D17 -> 0 | I172: =F172+G172-H172 -> 130.18 | J172: =Tank_Master!$E$9 -> 25 | K172: =Tank_Master!$D$9 -> 250 | L172: =IF(I172<J172-0.001,"BELOW MIN",IF(I172>K172+0.001,"ABOVE MAX","OK")) -> OK | M172: =IF(K172>0,I172/K172,0) -> 0.52072
... A190: TK-301 | B190: Naphtha | C190: Product | D190: 31 | E190: =Daily_Plan!B35 -> 46326 | F190: =I189 -> 93.38 | G190: =Daily_Plan!Y35 -> 9.6 | H190: =Product_Liftings!D35 -> 0 | I190: =F190+G190-H190 -> 102.98 | J190: =Tank_Master!$E$9 -> 25 | K190: =Tank_Master!$D$9 -> 250 | L190: =IF(I190<J190-0.001,"BELOW MIN",IF(I190>K190+0.001,"ABOVE MAX","OK")) -> OK | M190: =IF(K190>0,I190/K190,0) -> 0.41192
A191: TK-401 | B191: Gasoline 95 | C191: Product | D191: 1 | E191: =Daily_Plan!B5 -> 46296 | F191: =Tank_Master!$F$10 -> 180 | G191: =Daily_Plan!Z5 -> 35.12 | H191: =Product_Liftings!E5 -> 30 | I191: =F191+G191-H191 -> 185.12 | J191: =Tank_Master!$E$10 -> 40 | K191: =Tank_Master!$D$10 -> 400 | L191: =IF(I191<J191-0.001,"BELOW MIN",IF(I191>K191+0.001,"ABOVE MAX","OK")) -> OK | M191: =IF(K191>0,I191/K191,0) -> 0.4628
A192: TK-401 | B192: Gasoline 95 | C192: Product | D192: 2 | E192: =Daily_Plan!B6 -> 46297 | F192: =I191 -> 185.12 | G192: =Daily_Plan!Z6 -> 35.12 | H192: =Product_Liftings!E6 -> 30 | I192: =F192+G192-H192 -> 190.24 | J192: =Tank_Master!$E$10 -> 40 | K192: =Tank_Master!$D$10 -> 400 | L192: =IF(I192<J192-0.001,"BELOW MIN",IF(I192>K192+0.001,"ABOVE MAX","OK")) -> OK | M192: =IF(K192>0,I192/K192,0) -> 0.4756
A193: TK-401 | B193: Gasoline 95 | C193: Product | D193: 3 | E193: =Daily_Plan!B7 -> 46298 | F193: =I192 -> 190.24 | G193: =Daily_Plan!Z7 -> 36.48 | H193: =Product_Liftings!E7 -> 30 | I193: =F193+G193-H193 -> 196.72 | J193: =Tank_Master!$E$10 -> 40 | K193: =Tank_Master!$D$10 -> 400 | L193: =IF(I193<J193-0.001,"BELOW MIN",IF(I193>K193+0.001,"ABOVE MAX","OK")) -> OK | M193: =IF(K193>0,I193/K193,0) -> 0.4918
A194: TK-401 | B194: Gasoline 95 | C194: Product | D194: 4 | E194: =Daily_Plan!B8 -> 46299 | F194: =I193 -> 196.72 | G194: =Daily_Plan!Z8 -> 33.24 | H194: =Product_Liftings!E8 -> 30 | I194: =F194+G194-H194 -> 199.96 | J194: =Tank_Master!$E$10 -> 40 | K194: =Tank_Master!$D$10 -> 400 | L194: =IF(I194<J194-0.001,"BELOW MIN",IF(I194>K194+0.001,"ABOVE MAX","OK")) -> OK | M194: =IF(K194>0,I194/K194,0) -> 0.4999
A195: TK-401 | B195: Gasoline 95 | C195: Product | D195: 5 | E195: =Daily_Plan!B9 -> 46300 | F195: =I194 -> 199.96 | G195: =Daily_Plan!Z9 -> 30.52 | H195: =Product_Liftings!E9 -> 30 | I195: =F195+G195-H195 -> 200.48 | J195: =Tank_Master!$E$10 -> 40 | K195: =Tank_Master!$D$10 -> 400 | L195: =IF(I195<J195-0.001,"BELOW MIN",IF(I195>K195+0.001,"ABOVE MAX","OK")) -> OK | M195: =IF(K195>0,I195/K195,0) -> 0.5012
A196: TK-401 | B196: Gasoline 95 | C196: Product | D196: 6 | E196: =Daily_Plan!B10 -> 46301 | F196: =I195 -> 200.48 | G196: =Daily_Plan!Z10 -> 32.4 | H196: =Product_Liftings!E10 -> 30 | I196: =F196+G196-H196 -> 202.88 | J196: =Tank_Master!$E$10 -> 40 | K196: =Tank_Master!$D$10 -> 400 | L196: =IF(I196<J196-0.001,"BELOW MIN",IF(I196>K196+0.001,"ABOVE MAX","OK")) -> OK | M196: =IF(K196>0,I196/K196,0) -> 0.5072
A197: TK-401 | B197: Gasoline 95 | C197: Product | D197: 7 | E197: =Daily_Plan!B11 -> 46302 | F197: =I196 -> 202.88 | G197: =Daily_Plan!Z11 -> 35.12 | H197: =Product_Liftings!E11 -> 30 | I197: =F197+G197-H197 -> 208 | J197: =Tank_Master!$E$10 -> 40 | K197: =Tank_Master!$D$10 -> 400 | L197: =IF(I197<J197-0.001,"BELOW MIN",IF(I197>K197+0.001,"ABOVE MAX","OK")) -> OK | M197: =IF(K197>0,I197/K197,0) -> 0.52
A198: TK-401 | B198: Gasoline 95 | C198: Product | D198: 8 | E198: =Daily_Plan!B12 -> 46303 | F198: =I197 -> 208 | G198: =Daily_Plan!Z12 -> 35.64 | H198: =Product_Liftings!E12 -> 30 | I198: =F198+G198-H198 -> 213.64 | J198: =Tank_Master!$E$10 -> 40 | K198: =Tank_Master!$D$10 -> 400 | L198: =IF(I198<J198-0.001,"BELOW MIN",IF(I198>K198+0.001,"ABOVE MAX","OK")) -> OK | M198: =IF(K198>0,I198/K198,0) -> 0.5341
A199: TK-401 | B199: Gasoline 95 | C199: Product | D199: 9 | E199: =Daily_Plan!B13 -> 46304 | F199: =I198 -> 213.64 | G199: =Daily_Plan!Z13 -> 36.48 | H199: =Product_Liftings!E13 -> 30 | I199: =F199+G199-H199 -> 220.12 | J199: =Tank_Master!$E$10 -> 40 | K199: =Tank_Master!$D$10 -> 400 | L199: =IF(I199<J199-0.001,"BELOW MIN",IF(I199>K199+0.001,"ABOVE MAX","OK")) -> OK | M199: =IF(K199>0,I199/K199,0) -> 0.5503
A200: TK-401 | B200: Gasoline 95 | C200: Product | D200: 10 | E200: =Daily_Plan!B14 -> 46305 | F200: =I199 -> 220.12 | G200: =Daily_Plan!Z14 -> 35.12 | H200: =Product_Liftings!E14 -> 30 | I200: =F200+G200-H200 -> 225.24 | J200: =Tank_Master!$E$10 -> 40 | K200: =Tank_Master!$D$10 -> 400 | L200: =IF(I200<J200-0.001,"BELOW MIN",IF(I200>K200+0.001,"ABOVE MAX","OK")) -> OK | M200: =IF(K200>0,I200/K200,0) -> 0.5631
A201: TK-401 | B201: Gasoline 95 | C201: Product | D201: 11 | E201: =Daily_Plan!B15 -> 46306 | F201: =I200 -> 225.24 | G201: =Daily_Plan!Z15 -> 35.12 | H201: =Product_Liftings!E15 -> 30 | I201: =F201+G201-H201 -> 230.36 | J201: =Tank_Master!$E$10 -> 40 | K201: =Tank_Master!$D$10 -> 400 | L201: =IF(I201<J201-0.001,"BELOW MIN",IF(I201>K201+0.001,"ABOVE MAX","OK")) -> OK | M201: =IF(K201>0,I201/K201,0) -> 0.5759
A202: TK-401 | B202: Gasoline 95 | C202: Product | D202: 12 | E202: =Daily_Plan!B16 -> 46307 | F202: =I201 -> 230.36 | G202: =Daily_Plan!Z16 -> 35.12 | H202: =Product_Liftings!E16 -> 110 | I202: =F202+G202-H202 -> 155.48 | J202: =Tank_Master!$E$10 -> 40 | K202: =Tank_Master!$D$10 -> 400 | L202: =IF(I202<J202-0.001,"BELOW MIN",IF(I202>K202+0.001,"ABOVE MAX","OK")) -> OK | M202: =IF(K202>0,I202/K202,0) -> 0.3887
A203: TK-401 | B203: Gasoline 95 | C203: Product | D203: 13 | E203: =Daily_Plan!B17 -> 46308 | F203: =I202 -> 155.48 | G203: =Daily_Plan!Z17 -> 35.12 | H203: =Product_Liftings!E17 -> 30 | I203: =F203+G203-H203 -> 160.6 | J203: =Tank_Master!$E$10 -> 40 | K203: =Tank_Master!$D$10 -> 400 | L203: =IF(I203<J203-0.001,"BELOW MIN",IF(I203>K203+0.001,"ABOVE MAX","OK")) -> OK | M203: =IF(K203>0,I203/K203,0) -> 0.4015
...

Sheet Tank_Summary
A1: Tank Inventory Overview – closing inventory (kbbl) and fill %
A2: Wide view of Tank_Balance for quick visual checks. All values are links.
C3: Closing inventory (kbbl) | N3: Fill % of working capacity
A4: Day | B4: Date | C4: TK-101 Arab Light | D4: TK-102 Murban | E4: TK-103 Tapis | F4: TK-104 Kimanis | G4: TK-201 LPG | H4: TK-301 Naphtha | I4: TK-401 Gasoline 95 | J4: TK-501 Jet A-1 | K4: TK-601 Diesel B10 | L4: TK-701 Fuel Oil | N4: TK-101 Arab Light | O4: TK-102 Murban | P4: TK-103 Tapis | Q4: TK-104 Kimanis | R4: TK-201 LPG | S4: TK-301 Naphtha | T4: TK-401 Gasoline 95 | U4: TK-501 Jet A-1 | V4: TK-601 Diesel B10 | W4: TK-701 Fuel Oil
A5: 1 | B5: =Daily_Plan!B5 -> 46296 | C5: =Tank_Balance!I5 -> 660 | D5: =Tank_Balance!I36 -> 460 | E5: =Tank_Balance!I67 -> 410 | F5: =Tank_Balance!I98 -> 350 | G5: =Tank_Balance!I129 -> 32.32 | H5: =Tank_Balance!I160 -> 119.6 | I5: =Tank_Balance!I191 -> 185.12 | J5: =Tank_Balance!I222 -> 145.3 | K5: =Tank_Balance!I253 -> 238.2768 | L5: =Tank_Balance!I284 -> 201.32 | N5: =Tank_Balance!M5 -> 0.44 | O5: =Tank_Balance!M36 -> 0.46 | P5: =Tank_Balance!M67 -> 0.45555556 | Q5: =Tank_Balance!M98 -> 0.4375 | R5: =Tank_Balance!M129 -> 0.53866667 | S5: =Tank_Balance!M160 -> 0.4784 | T5: =Tank_Balance!M191 -> 0.4628 | U5: =Tank_Balance!M222 -> 0.48433333 | V5: =Tank_Balance!M253 -> 0.4765536 | W5: =Tank_Balance!M284 -> 0.5033
A6: 2 | B6: =Daily_Plan!B6 -> 46297 | C6: =Tank_Balance!I6 -> 620 | D6: =Tank_Balance!I37 -> 420 | E6: =Tank_Balance!I68 -> 370 | F6: =Tank_Balance!I99 -> 320 | G6: =Tank_Balance!I130 -> 34.64 | H6: =Tank_Balance!I161 -> 129.2 | I6: =Tank_Balance!I192 -> 190.24 | J6: =Tank_Balance!I223 -> 150.6 | K6: =Tank_Balance!I254 -> 246.5536 | L6: =Tank_Balance!I285 -> 222.64 | N6: =Tank_Balance!M6 -> 0.41333333 | O6: =Tank_Balance!M37 -> 0.42 | P6: =Tank_Balance!M68 -> 0.41111111 | Q6: =Tank_Balance!M99 -> 0.4 | R6: =Tank_Balance!M130 -> 0.57733333 | S6: =Tank_Balance!M161 -> 0.5168 | T6: =Tank_Balance!M192 -> 0.4756 | U6: =Tank_Balance!M223 -> 0.502 | V6: =Tank_Balance!M254 -> 0.4931072 | W6: =Tank_Balance!M285 -> 0.5566
A7: 3 | B7: =Daily_Plan!B7 -> 46298 | C7: =Tank_Balance!I7 -> 579 | D7: =Tank_Balance!I38 -> 382 | E7: =Tank_Balance!I69 -> 329 | F7: =Tank_Balance!I100 -> 290 | G7: =Tank_Balance!I131 -> 37.21 | H7: =Tank_Balance!I162 -> 137.72 | I7: =Tank_Balance!I193 -> 196.72 | J7: =Tank_Balance!I224 -> 155.89 | K7: =Tank_Balance!I255 -> 255.0656 | L7: =Tank_Balance!I286 -> 243.06 | N7: =Tank_Balance!M7 -> 0.386 | O7: =Tank_Balance!M38 -> 0.382 | P7: =Tank_Balance!M69 -> 0.36555556 | Q7: =Tank_Balance!M100 -> 0.3625 | R7: =Tank_Balance!M131 -> 0.62016667 | S7: =Tank_Balance!M162 -> 0.55088 | T7: =Tank_Balance!M193 -> 0.4918 | U7: =Tank_Balance!M224 -> 0.51963333 | V7: =Tank_Balance!M255 -> 0.5101312 | W7: =Tank_Balance!M286 -> 0.60765
A8: 4 | B8: =Daily_Plan!B8 -> 46299 | C8: =Tank_Balance!I8 -> 540 | D8: =Tank_Balance!I39 -> 346 | E8: =Tank_Balance!I70 -> 290 | F8: =Tank_Balance!I101 -> 262 | G8: =Tank_Balance!I132 -> 38.88 | H8: =Tank_Balance!I163 -> 146.56 | I8: =Tank_Balance!I194 -> 199.96 | J8: =Tank_Balance!I225 -> 159.94 | K8: =Tank_Balance!I256 -> 261.01 | L8: =Tank_Balance!I287 -> 263.58 | N8: =Tank_Balance!M8 -> 0.36 | O8: =Tank_Balance!M39 -> 0.346 | P8: =Tank_Balance!M70 -> 0.32222222 | Q8: =Tank_Balance!M101 -> 0.3275 | R8: =Tank_Balance!M132 -> 0.648 | S8: =Tank_Balance!M163 -> 0.58624 | T8: =Tank_Balance!M194 -> 0.4999 | U8: =Tank_Balance!M225 -> 0.53313333 | V8: =Tank_Balance!M256 -> 0.52202 | W8: =Tank_Balance!M287 -> 0.65895
A9: 5 | B9: =Daily_Plan!B9 -> 46300 | C9: =Tank_Balance!I9 -> 505 | D9: =Tank_Balance!I40 -> 812 | E9: =Tank_Balance!I71 -> 253 | F9: =Tank_Balance!I102 -> 236 | G9: =Tank_Balance!I133 -> 39.79 | H9: =Tank_Balance!I164 -> 155.36 | I9: =Tank_Balance!I195 -> 200.48 | J9: =Tank_Balance!I226 -> 162.47 | K9: =Tank_Balance!I257 -> 264.1712 | L9: =Tank_Balance!I288 -> 282.36 | N9: =Tank_Balance!M9 -> 0.33666667 | O9: =Tank_Balance!M40 -> 0.812 | P9: =Tank_Balance!M71 -> 0.28111111 | Q9: =Tank_Balance!M102 -> 0.295 | R9: =Tank_Balance!M133 -> 0.66316667 | S9: =Tank_Balance!M164 -> 0.62144 | T9: =Tank_Balance!M195 -> 0.5012 | U9: =Tank_Balance!M226 -> 0.54156667 | V9: =Tank_Balance!M257 -> 0.5283424 | W9: =Tank_Balance!M288 -> 0.7059
A10: 6 | B10: =Daily_Plan!B10 -> 46301 | C10: =Tank_Balance!I10 -> 468 | D10: =Tank_Balance!I41 -> 776 | E10: =Tank_Balance!I72 -> 615 | F10: =Tank_Balance!I103 -> 208 | G10: =Tank_Balance!I134 -> 41.31 | H10: =Tank_Balance!I165 -> 164.62 | I10: =Tank_Balance!I196 -> 202.88 | J10: =Tank_Balance!I227 -> 166.07 | K10: =Tank_Balance!I258 -> 269.4296 | L10: =Tank_Balance!I289 -> 101.71 | N10: =Tank_Balance!M10 -> 0.312 | O10: =Tank_Balance!M41 -> 0.776 | P10: =Tank_Balance!M72 -> 0.68333333 | Q10: =Tank_Balance!M103 -> 0.26 | R10: =Tank_Balance!M134 -> 0.6885 | S10: =Tank_Balance!M165 -> 0.65848 | T10: =Tank_Balance!M196 -> 0.5072 | U10: =Tank_Balance!M227 -> 0.55356667 | V10: =Tank_Balance!M258 -> 0.5388592 | W10: =Tank_Balance!M289 -> 0.254275
A11: 7 | B11: =Daily_Plan!B11 -> 46302 | C11: =Tank_Balance!I11 -> 429 | D11: =Tank_Balance!I42 -> 738 | E11: =Tank_Balance!I73 -> 575 | F11: =Tank_Balance!I104 -> 178 | G11: =Tank_Balance!I135 -> 43.55 | H11: =Tank_Balance!I166 -> 173.56 | I11: =Tank_Balance!I197 -> 208 | J11: =Tank_Balance!I228 -> 85.91 | K11: =Tank_Balance!I259 -> 277.0792 | L11: =Tank_Balance!I290 -> 121.9 | N11: =Tank_Balance!M11 -> 0.286 | O11: =Tank_Balance!M42 -> 0.738 | P11: =Tank_Balance!M73 -> 0.63888889 | Q11: =Tank_Balance!M104 -> 0.2225 | R11: =Tank_Balance!M135 -> 0.72583333 | S11: =Tank_Balance!M166 -> 0.69424 | T11: =Tank_Balance!M197 -> 0.52 | U11: =Tank_Balance!M228 -> 0.28636667 | V11: =Tank_Balance!M259 -> 0.5541584 | W11: =Tank_Balance!M290 -> 0.30475
A12: 8 | B12: =Daily_Plan!B12 -> 46303 | C12: =Tank_Balance!I12 -> 989 | D12: =Tank_Balance!I43 -> 698 | E12: =Tank_Balance!I74 -> 535 | F12: =Tank_Balance!I105 -> 148 | G12: =Tank_Balance!I136 -> 46.05 | H12: =Tank_Balance!I167 -> 183.16 | I12: =Tank_Balance!I198 -> 213.64 | J12: =Tank_Balance!I229 -> 91.21 | K12: =Tank_Balance!I260 -> 285.5324 | L12: =Tank_Balance!I291 -> 142.28 | N12: =Tank_Balance!M12 -> 0.65933333 | O12: =Tank_Balance!M43 -> 0.698 | P12: =Tank_Balance!M74 -> 0.59444444 | Q12: =Tank_Balance!M105 -> 0.185 | R12: =Tank_Balance!M136 -> 0.7675 | S12: =Tank_Balance!M167 -> 0.73264 | T12: =Tank_Balance!M198 -> 0.5341 | U12: =Tank_Balance!M229 -> 0.30403333 | V12: =Tank_Balance!M260 -> 0.5710648 | W12: =Tank_Balance!M291 -> 0.3557
A13: 9 | B13: =Daily_Plan!B13 -> 46304 | C13: =Tank_Balance!I13 -> 949 | D13: =Tank_Balance!I44 -> 658 | E13: =Tank_Balance!I75 -> 494 | F13: =Tank_Balance!I106 -> 119 | G13: =Tank_Balance!I137 -> 48.64 | H13: =Tank_Balance!I168 -> 91.78 | I13: =Tank_Balance!I199 -> 220.12 | J13: =Tank_Balance!I230 -> 96.53 | K13: =Tank_Balance!I261 -> 293.966 | L13: =Tank_Balance!I292 -> 162.63 | N13: =Tank_Balance!M13 -> 0.63266667 | O13: =Tank_Balance!M44 -> 0.658 | P13: =Tank_Balance!M75 -> 0.54888889 | Q13: =Tank_Balance!M106 -> 0.14875 | R13: =Tank_Balance!M137 -> 0.81066667 | S13: =Tank_Balance!M168 -> 0.36712 | T13: =Tank_Balance!M199 -> 0.5503 | U13: =Tank_Balance!M230 -> 0.32176667 | V13: =Tank_Balance!M261 -> 0.587932 | W13: =Tank_Balance!M292 -> 0.406575
A14: 10 | B14: =Daily_Plan!B14 -> 46305 | C14: =Tank_Balance!I14 -> 909 | D14: =Tank_Balance!I45 -> 618 | E14: =Tank_Balance!I76 -> 454 | F14: =Tank_Balance!I107 -> 439 | G14: =Tank_Balance!I138 -> 20.96 | H14: =Tank_Balance!I169 -> 101.38 | I14: =Tank_Balance!I200 -> 225.24 | J14: =Tank_Balance!I231 -> 101.83 | K14: =Tank_Balance!I262 -> 302.2428 | L14: =Tank_Balance!I293 -> 183.95 | N14: =Tank_Balance!M14 -> 0.606 | O14: =Tank_Balance!M45 -> 0.618 | P14: =Tank_Balance!M76 -> 0.50444444 | Q14: =Tank_Balance!M107 -> 0.54875 | R14: =Tank_Balance!M138 -> 0.34933333 | S14: =Tank_Balance!M169 -> 0.40552 | T14: =Tank_Balance!M200 -> 0.5631 | U14: =Tank_Balance!M231 -> 0.33943333 | V14: =Tank_Balance!M262 -> 0.6044856 | W14: =Tank_Balance!M293 -> 0.459875
A15: 11 | B15: =Daily_Plan!B15 -> 46306 | C15: =Tank_Balance!I15 -> 869 | D15: =Tank_Balance!I46 -> 578 | E15: =Tank_Balance!I77 -> 414 | F15: =Tank_Balance!I108 -> 409 | G15: =Tank_Balance!I139 -> 23.28 | H15: =Tank_Balance!I170 -> 110.98 | I15: =Tank_Balance!I201 -> 230.36 | J15: =Tank_Balance!I232 -> 107.13 | K15: =Tank_Balance!I263 -> 170.5196 | L15: =Tank_Balance!I294 -> 205.27 | N15: =Tank_Balance!M15 -> 0.57933333 | O15: =Tank_Balance!M46 -> 0.578 | P15: =Tank_Balance!M77 -> 0.46 | Q15: =Tank_Balance!M108 -> 0.51125 | R15: =Tank_Balance!M139 -> 0.388 | S15: =Tank_Balance!M170 -> 0.44392 | T15: =Tank_Balance!M201 -> 0.5759 | U15: =Tank_Balance!M232 -> 0.3571 | V15: =Tank_Balance!M263 -> 0.3410392 | W15: =Tank_Balance!M294 -> 0.513175
A16: 12 | B16: =Daily_Plan!B16 -> 46307 | C16: =Tank_Balance!I16 -> 829 | D16: =Tank_Balance!I47 -> 538 | E16: =Tank_Balance!I78 -> 374 | F16: =Tank_Balance!I109 -> 379 | G16: =Tank_Balance!I140 -> 25.6 | H16: =Tank_Balance!I171 -> 120.58 | I16: =Tank_Balance!I202 -> 155.48 | J16: =Tank_Balance!I233 -> 112.43 | K16: =Tank_Balance!I264 -> 178.7964 | L16: =Tank_Balance!I295 -> 226.59 | N16: =Tank_Balance!M16 -> 0.55266667 | O16: =Tank_Balance!M47 -> 0.538 | P16: =Tank_Balance!M78 -> 0.41555556 | Q16: =Tank_Balance!M109 -> 0.47375 | R16: =Tank_Balance!M140 -> 0.42666667 | S16: =Tank_Balance!M171 -> 0.48232 | T16: =Tank_Balance!M202 -> 0.3887 | U16: =Tank_Balance!M233 -> 0.37476667 | V16: =Tank_Balance!M264 -> 0.3575928 | W16: =Tank_Balance!M295 -> 0.566475
... A35: 31 | B35: =Daily_Plan!B35 -> 46326 | C35: =Tank_Balance!I35 -> 569 | D35: =Tank_Balance!I66 -> 278 | E35: =Tank_Balance!I97 -> 414 | F35: =Tank_Balance!I128 -> 159 | G35: =Tank_Balance!I159 -> 39.68 | H35: =Tank_Balance!I190 -> 102.98 | I35: =Tank_Balance!I221 -> 172.76 | J35: =Tank_Balance!I252 -> 128.13 | K35: =Tank_Balance!I283 -> 196.0556 | L35: =Tank_Balance!I314 -> 231.67 | N35: =Tank_Balance!M35 -> 0.37933333 | O35: =Tank_Balance!M66 -> 0.278 | P35: =Tank_Balance!M97 -> 0.46 | Q35: =Tank_Balance!M128 -> 0.19875 | R35: =Tank_Balance!M159 -> 0.66133333 | S35: =Tank_Balance!M190 -> 0.41192 | T35: =Tank_Balance!M221 -> 0.4319 | U35: =Tank_Balance!M252 -> 0.4271 | V35: =Tank_Balance!M283 -> 0.3921112 | W35: =Tank_Balance!M314 -> 0.579175

Sheet Constraint_Check
A1: Constraint Check – does the current plan satisfy every plant constraint?
A2: Re-evaluates automatically when the optimizer writes new decision variables into Daily_Plan. VIOL = constraint breached.
A4: Day | B4: Date | C4: Status | D4: CDU rate | E4: C1 CDU cap | F4: Crude max | G4: C2 Crude rate | H4: CDU Δ vs prev day | I4: C3 Ramp | J4: Reformer feed | K4: C4 Ref cap | L4: C5 Naph avail | M4: RFCC feed | N4: C6 RFCC cap | O4: C7 Resid avail | P4: DHT feed | Q4: C8 DHT cap | R4: Gasoline RON | S4: C9 RON spec | T4: Residue S wt% | U4: C10 Sulfur | V4: Tank breaches | W4: C13 Tank limits | X4: Day result
A5: 1 | B5: =Daily_Plan!B5 -> 46296 | C5: =Daily_Plan!C5 -> Actual | D5: =Daily_Plan!J5 -> 150 | E5: =IF(AND(D5>=Unit_Data!$D$5-0.001,D5<=Unit_Data!$D$4+0.001),"OK","VIOL") -> OK | F5: =SUMPRODUCT(--(Daily_Plan!D5:G5>Crude_Data!$C$13:$F$13+0.001))+SUMPRODUCT(--(Daily_Plan!D5:G5<Crude_Data!$C$14:$F$14-0.001)) -> 0 | G5: =IF(F5=0,"OK","VIOL") -> OK | H5: n/a | I5: n/a | J5: =Daily_Plan!H5 -> 22 | K5: =IF(AND(J5>=Unit_Data!$D$9-0.001,J5<=Unit_Data!$D$8+0.001),"OK","VIOL") -> OK | L5: =IF(J5<=Daily_Plan!L5+0.001,"OK","VIOL") -> OK | M5: =Daily_Plan!I5 -> 32 | N5: =IF(AND(M5>=Unit_Data!$D$15-0.001,M5<=Unit_Data!$D$14+0.001),"OK","VIOL") -> OK | O5: =IF(M5<=Daily_Plan!O5+0.001,"OK","VIOL") -> OK | P5: =Daily_Plan!W5 -> 44.16 | Q5: =IF(AND(P5>=Unit_Data!$D$23-0.001,P5<=Unit_Data!$D$22+0.001),"OK","VIOL") -> OK | R5: =Daily_Plan!AD5 -> 95.157175 | S5: =IF(R5>=Unit_Data!$D$28-0.001,"OK","VIOL") -> OK | T5: =Daily_Plan!P5 -> 1.4610895 | U5: =IF(T5<=Unit_Data!$D$29+0.0001,"OK","VIOL") -> OK | V5: =COUNTIFS(Tank_Balance!$D$5:$D$314,A5,Tank_Balance!$L$5:$L$314,"<>OK") -> 0 | W5: =IF(V5=0,"OK","VIOL") -> OK | X5: =IF(COUNTIF(E5:W5,"VIOL")=0,"FEASIBLE","INFEASIBLE") -> FEASIBLE
A6: 2 | B6: =Daily_Plan!B6 -> 46297 | C6: =Daily_Plan!C6 -> Actual | D6: =Daily_Plan!J6 -> 150 | E6: =IF(AND(D6>=Unit_Data!$D$5-0.001,D6<=Unit_Data!$D$4+0.001),"OK","VIOL") -> OK | F6: =SUMPRODUCT(--(Daily_Plan!D6:G6>Crude_Data!$C$13:$F$13+0.001))+SUMPRODUCT(--(Daily_Plan!D6:G6<Crude_Data!$C$14:$F$14-0.001)) -> 0 | G6: =IF(F6=0,"OK","VIOL") -> OK | H6: =D6-D5 -> 0 | I6: =IF(ABS(H6)<=Unit_Data!$D$6+0.001,"OK","VIOL") -> OK | J6: =Daily_Plan!H6 -> 22 | K6: =IF(AND(J6>=Unit_Data!$D$9-0.001,J6<=Unit_Data!$D$8+0.001),"OK","VIOL") -> OK | L6: =IF(J6<=Daily_Plan!L6+0.001,"OK","VIOL") -> OK | M6: =Daily_Plan!I6 -> 32 | N6: =IF(AND(M6>=Unit_Data!$D$15-0.001,M6<=Unit_Data!$D$14+0.001),"OK","VIOL") -> OK | O6: =IF(M6<=Daily_Plan!O6+0.001,"OK","VIOL") -> OK | P6: =Daily_Plan!W6 -> 44.16 | Q6: =IF(AND(P6>=Unit_Data!$D$23-0.001,P6<=Unit_Data!$D$22+0.001),"OK","VIOL") -> OK | R6: =Daily_Plan!AD6 -> 95.157175 | S6: =IF(R6>=Unit_Data!$D$28-0.001,"OK","VIOL") -> OK | T6: =Daily_Plan!P6 -> 1.4610895 | U6: =IF(T6<=Unit_Data!$D$29+0.0001,"OK","VIOL") -> OK | V6: =COUNTIFS(Tank_Balance!$D$5:$D$314,A6,Tank_Balance!$L$5:$L$314,"<>OK") -> 0 | W6: =IF(V6=0,"OK","VIOL") -> OK | X6: =IF(COUNTIF(E6:W6,"VIOL")=0,"FEASIBLE","INFEASIBLE") -> FEASIBLE
A7: 3 | B7: =Daily_Plan!B7 -> 46298 | C7: =Daily_Plan!C7 -> Actual | D7: =Daily_Plan!J7 -> 150 | E7: =IF(AND(D7>=Unit_Data!$D$5-0.001,D7<=Unit_Data!$D$4+0.001),"OK","VIOL") -> OK | F7: =SUMPRODUCT(--(Daily_Plan!D7:G7>Crude_Data!$C$13:$F$13+0.001))+SUMPRODUCT(--(Daily_Plan!D7:G7<Crude_Data!$C$14:$F$14-0.001)) -> 0 | G7: =IF(F7=0,"OK","VIOL") -> OK | H7: =D7-D6 -> 0 | I7: =IF(ABS(H7)<=Unit_Data!$D$6+0.001,"OK","VIOL") -> OK | J7: =Daily_Plan!H7 -> 23 | K7: =IF(AND(J7>=Unit_Data!$D$9-0.001,J7<=Unit_Data!$D$8+0.001),"OK","VIOL") -> OK | L7: =IF(J7<=Daily_Plan!L7+0.001,"OK","VIOL") -> OK | M7: =Daily_Plan!I7 -> 33 | N7: =IF(AND(M7>=Unit_Data!$D$15-0.001,M7<=Unit_Data!$D$14+0.001),"OK","VIOL") -> OK | O7: =IF(M7<=Daily_Plan!O7+0.001,"OK","VIOL") -> OK | P7: =Daily_Plan!W7 -> 44.4 | Q7: =IF(AND(P7>=Unit_Data!$D$23-0.001,P7<=Unit_Data!$D$22+0.001),"OK","VIOL") -> OK | R7: =Daily_Plan!AD7 -> 95.177632 | S7: =IF(R7>=Unit_Data!$D$28-0.001,"OK","VIOL") -> OK | T7: =Daily_Plan!P7 -> 1.4697998 | U7: =IF(T7<=Unit_Data!$D$29+0.0001,"OK","VIOL") -> OK | V7: =COUNTIFS(Tank_Balance!$D$5:$D$314,A7,Tank_Balance!$L$5:$L$314,"<>OK") -> 0 | W7: =IF(V7=0,"OK","VIOL") -> OK | X7: =IF(COUNTIF(E7:W7,"VIOL")=0,"FEASIBLE","INFEASIBLE") -> FEASIBLE
A8: 4 | B8: =Daily_Plan!B8 -> 46299 | C8: =Daily_Plan!C8 -> Actual | D8: =Daily_Plan!J8 -> 142 | E8: =IF(AND(D8>=Unit_Data!$D$5-0.001,D8<=Unit_Data!$D$4+0.001),"OK","VIOL") -> OK | F8: =SUMPRODUCT(--(Daily_Plan!D8:G8>Crude_Data!$C$13:$F$13+0.001))+SUMPRODUCT(--(Daily_Plan!D8:G8<Crude_Data!$C$14:$F$14-0.001)) -> 0 | G8: =IF(F8=0,"OK","VIOL") -> OK | H8: =D8-D7 -> -8 | I8: =IF(ABS(H8)<=Unit_Data!$D$6+0.001,"OK","VIOL") -> OK | J8: =Daily_Plan!H8 -> 21 | K8: =IF(AND(J8>=Unit_Data!$D$9-0.001,J8<=Unit_Data!$D$8+0.001),"OK","VIOL") -> OK | L8: =IF(J8<=Daily_Plan!L8+0.001,"OK","VIOL") -> OK | M8: =Daily_Plan!I8 -> 30 | N8: =IF(AND(M8>=Unit_Data!$D$15-0.001,M8<=Unit_Data!$D$14+0.001),"OK","VIOL") -> OK | O8: =IF(M8<=Daily_Plan!O8+0.001,"OK","VIOL") -> OK | P8: =Daily_Plan!W8 -> 41.78 | Q8: =IF(AND(P8>=Unit_Data!$D$23-0.001,P8<=Unit_Data!$D$22+0.001),"OK","VIOL") -> OK | R8: =Daily_Plan!AD8 -> 95.184116 | S8: =IF(R8>=Unit_Data!$D$28-0.001,"OK","VIOL") -> OK | T8: =Daily_Plan!P8 -> 1.4741687 | U8: =IF(T8<=Unit_Data!$D$29+0.0001,"OK","VIOL") -> OK | V8: =COUNTIFS(Tank_Balance!$D$5:$D$314,A8,Tank_Balance!$L$5:$L$314,"<>OK") -> 0 | W8: =IF(V8=0,"OK","VIOL") -> OK | X8: =IF(COUNTIF(E8:W8,"VIOL")=0,"FEASIBLE","INFEASIBLE") -> FEASIBLE
A9: 5 | B9: =Daily_Plan!B9 -> 46300 | C9: =Daily_Plan!C9 -> Actual | D9: =Daily_Plan!J9 -> 132 | E9: =IF(AND(D9>=Unit_Data!$D$5-0.001,D9<=Unit_Data!$D$4+0.001),"OK","VIOL") -> OK | F9: =SUMPRODUCT(--(Daily_Plan!D9:G9>Crude_Data!$C$13:$F$13+0.001))+SUMPRODUCT(--(Daily_Plan!D9:G9<Crude_Data!$C$14:$F$14-0.001)) -> 0 | G9: =IF(F9=0,"OK","VIOL") -> OK | H9: =D9-D8 -> -10 | I9: =IF(ABS(H9)<=Unit_Data!$D$6+0.001,"OK","VIOL") -> OK | J9: =Daily_Plan!H9 -> 19 | K9: =IF(AND(J9>=Unit_Data!$D$9-0.001,J9<=Unit_Data!$D$8+0.001),"OK","VIOL") -> OK | L9: =IF(J9<=Daily_Plan!L9+0.001,"OK","VIOL") -> OK | M9: =Daily_Plan!I9 -> 28 | N9: =IF(AND(M9>=Unit_Data!$D$15-0.001,M9<=Unit_Data!$D$14+0.001),"OK","VIOL") -> OK | O9: =IF(M9<=Daily_Plan!O9+0.001,"OK","VIOL") -> OK | P9: =Daily_Plan!W9 -> 38.94 | Q9: =IF(AND(P9>=Unit_Data!$D$23-0.001,P9<=Unit_Data!$D$22+0.001),"OK","VIOL") -> OK | R9: =Daily_Plan!AD9 -> 95.137615 | S9: =IF(R9>=Unit_Data!$D$28-0.001,"OK","VIOL") -> OK | T9: =Daily_Plan!P9 -> 1.4487029 | U9: =IF(T9<=Unit_Data!$D$29+0.0001,"OK","VIOL") -> OK | V9: =COUNTIFS(Tank_Balance!$D$5:$D$314,A9,Tank_Balance!$L$5:$L$314,"<>OK") -> 0 | W9: =IF(V9=0,"OK","VIOL") -> OK | X9: =IF(COUNTIF(E9:W9,"VIOL")=0,"FEASIBLE","INFEASIBLE") -> FEASIBLE
A10: 6 | B10: =Daily_Plan!B10 -> 46301 | C10: =Daily_Plan!C10 -> Actual | D10: =Daily_Plan!J10 -> 139 | E10: =IF(AND(D10>=Unit_Data!$D$5-0.001,D10<=Unit_Data!$D$4+0.001),"OK","VIOL") -> OK | F10: =SUMPRODUCT(--(Daily_Plan!D10:G10>Crude_Data!$C$13:$F$13+0.001))+SUMPRODUCT(--(Daily_Plan!D10:G10<Crude_Data!$C$14:$F$14-0.001)) -> 0 | G10: =IF(F10=0,"OK","VIOL") -> OK | H10: =D10-D9 -> 7 | I10: =IF(ABS(H10)<=Unit_Data!$D$6+0.001,"OK","VIOL") -> OK | J10: =Daily_Plan!H10 -> 20 | K10: =IF(AND(J10>=Unit_Data!$D$9-0.001,J10<=Unit_Data!$D$8+0.001),"OK","VIOL") -> OK | L10: =IF(J10<=Daily_Plan!L10+0.001,"OK","VIOL") -> OK | M10: =Daily_Plan!I10 -> 30 | N10: =IF(AND(M10>=Unit_Data!$D$15-0.001,M10<=Unit_Data!$D$14+0.001),"OK","VIOL") -> OK | O10: =IF(M10<=Daily_Plan!O10+0.001,"OK","VIOL") -> OK | P10: =Daily_Plan!W10 -> 41.08 | Q10: =IF(AND(P10>=Unit_Data!$D$23-0.001,P10<=Unit_Data!$D$22+0.001),"OK","VIOL") -> OK | R10: =Daily_Plan!AD10 -> 95.111111 | S10: =IF(R10>=Unit_Data!$D$28-0.001,"OK","VIOL") -> OK | T10: =Daily_Plan!P10 -> 1.4528076 | U10: =IF(T10<=Unit_Data!$D$29+0.0001,"OK","VIOL") -> OK | V10: =COUNTIFS(Tank_Balance!$D$5:$D$314,A10,Tank_Balance!$L$5:$L$314,"<>OK") -> 0 | W10: =IF(V10=0,"OK","VIOL") -> OK | X10: =IF(COUNTIF(E10:W10,"VIOL")=0,"FEASIBLE","INFEASIBLE") -> FEASIBLE
A11: 7 | B11: =Daily_Plan!B11 -> 46302 | C11: =Daily_Plan!C11 -> Actual | D11: =Daily_Plan!J11 -> 147 | E11: =IF(AND(D11>=Unit_Data!$D$5-0.001,D11<=Unit_Data!$D$4+0.001),"OK","VIOL") -> OK | F11: =SUMPRODUCT(--(Daily_Plan!D11:G11>Crude_Data!$C$13:$F$13+0.001))+SUMPRODUCT(--(Daily_Plan!D11:G11<Crude_Data!$C$14:$F$14-0.001)) -> 0 | G11: =IF(F11=0,"OK","VIOL") -> OK | H11: =D11-D10 -> 8 | I11: =IF(ABS(H11)<=Unit_Data!$D$6+0.001,"OK","VIOL") -> OK | J11: =Daily_Plan!H11 -> 22 | K11: =IF(AND(J11>=Unit_Data!$D$9-0.001,J11<=Unit_Data!$D$8+0.001),"OK","VIOL") -> OK | L11: =IF(J11<=Daily_Plan!L11+0.001,"OK","VIOL") -> OK | M11: =Daily_Plan!I11 -> 32 | N11: =IF(AND(M11>=Unit_Data!$D$15-0.001,M11<=Unit_Data!$D$14+0.001),"OK","VIOL") -> OK | O11: =IF(M11<=Daily_Plan!O11+0.001,"OK","VIOL") -> OK | P11: =Daily_Plan!W11 -> 43.52 | Q11: =IF(AND(P11>=Unit_Data!$D$23-0.001,P11<=Unit_Data!$D$22+0.001),"OK","VIOL") -> OK | R11: =Daily_Plan!AD11 -> 95.157175 | S11: =IF(R11>=Unit_Data!$D$28-0.001,"OK","VIOL") -> OK | T11: =Daily_Plan!P11 -> 1.4494927 | U11: =IF(T11<=Unit_Data!$D$29+0.0001,"OK","VIOL") -> OK | V11: =COUNTIFS(Tank_Balance!$D$5:$D$314,A11,Tank_Balance!$L$5:$L$314,"<>OK") -> 0 | W11: =IF(V11=0,"OK","VIOL") -> OK | X11: =IF(COUNTIF(E11:W11,"VIOL")=0,"FEASIBLE","INFEASIBLE") -> FEASIBLE
A12: 8 | B12: =Daily_Plan!B12 -> 46303 | C12: =Daily_Plan!C12 -> Actual | D12: =Daily_Plan!J12 -> 150 | E12: =IF(AND(D12>=Unit_Data!$D$5-0.001,D12<=Unit_Data!$D$4+0.001),"OK","VIOL") -> OK | F12: =SUMPRODUCT(--(Daily_Plan!D12:G12>Crude_Data!$C$13:$F$13+0.001))+SUMPRODUCT(--(Daily_Plan!D12:G12<Crude_Data!$C$14:$F$14-0.001)) -> 0 | G12: =IF(F12=0,"OK","VIOL") -> OK | H12: =D12-D11 -> 3 | I12: =IF(ABS(H12)<=Unit_Data!$D$6+0.001,"OK","VIOL") -> OK | J12: =Daily_Plan!H12 -> 22 | K12: =IF(AND(J12>=Unit_Data!$D$9-0.001,J12<=Unit_Data!$D$8+0.001),"OK","VIOL") -> OK | L12: =IF(J12<=Daily_Plan!L12+0.001,"OK","VIOL") -> OK | M12: =Daily_Plan!I12 -> 33 | N12: =IF(AND(M12>=Unit_Data!$D$15-0.001,M12<=Unit_Data!$D$14+0.001),"OK","VIOL") -> OK | O12: =IF(M12<=Daily_Plan!O12+0.001,"OK","VIOL") -> OK | P12: =Daily_Plan!W12 -> 44.34 | Q12: =IF(AND(P12>=Unit_Data!$D$23-0.001,P12<=Unit_Data!$D$22+0.001),"OK","VIOL") -> OK | R12: =Daily_Plan!AD12 -> 95.111111 | S12: =IF(R12>=Unit_Data!$D$28-0.001,"OK","VIOL") -> OK | T12: =Daily_Plan!P12 -> 1.4610895 | U12: =IF(T12<=Unit_Data!$D$29+0.0001,"OK","VIOL") -> OK | V12: =COUNTIFS(Tank_Balance!$D$5:$D$314,A12,Tank_Balance!$L$5:$L$314,"<>OK") -> 0 | W12: =IF(V12=0,"OK","VIOL") -> OK | X12: =IF(COUNTIF(E12:W12,"VIOL")=0,"FEASIBLE","INFEASIBLE") -> FEASIBLE
A13: 9 | B13: =Daily_Plan!B13 -> 46304 | C13: =Daily_Plan!C13 -> Actual | D13: =Daily_Plan!J13 -> 150 | E13: =IF(AND(D13>=Unit_Data!$D$5-0.001,D13<=Unit_Data!$D$4+0.001),"OK","VIOL") -> OK | F13: =SUMPRODUCT(--(Daily_Plan!D13:G13>Crude_Data!$C$13:$F$13+0.001))+SUMPRODUCT(--(Daily_Plan!D13:G13<Crude_Data!$C$14:$F$14-0.001)) -> 0 | G13: =IF(F13=0,"OK","VIOL") -> OK | H13: =D13-D12 -> 0 | I13: =IF(ABS(H13)<=Unit_Data!$D$6+0.001,"OK","VIOL") -> OK | J13: =Daily_Plan!H13 -> 23 | K13: =IF(AND(J13>=Unit_Data!$D$9-0.001,J13<=Unit_Data!$D$8+0.001),"OK","VIOL") -> OK | L13: =IF(J13<=Daily_Plan!L13+0.001,"OK","VIOL") -> OK | M13: =Daily_Plan!I13 -> 33 | N13: =IF(AND(M13>=Unit_Data!$D$15-0.001,M13<=Unit_Data!$D$14+0.001),"OK","VIOL") -> OK | O13: =IF(M13<=Daily_Plan!O13+0.001,"OK","VIOL") -> OK | P13: =Daily_Plan!W13 -> 44.32 | Q13: =IF(AND(P13>=Unit_Data!$D$23-0.001,P13<=Unit_Data!$D$22+0.001),"OK","VIOL") -> OK | R13: =Daily_Plan!AD13 -> 95.177632 | S13: =IF(R13>=Unit_Data!$D$28-0.001,"OK","VIOL") -> OK | T13: =Daily_Plan!P13 -> 1.4615632 | U13: =IF(T13<=Unit_Data!$D$29+0.0001,"OK","VIOL") -> OK | V13: =COUNTIFS(Tank_Balance!$D$5:$D$314,A13,Tank_Balance!$L$5:$L$314,"<>OK") -> 0 | W13: =IF(V13=0,"OK","VIOL") -> OK | X13: =IF(COUNTIF(E13:W13,"VIOL")=0,"FEASIBLE","INFEASIBLE") -> FEASIBLE
A14: 10 | B14: =Daily_Plan!B14 -> 46305 | C14: =Daily_Plan!C14 -> Actual | D14: =Daily_Plan!J14 -> 150 | E14: =IF(AND(D14>=Unit_Data!$D$5-0.001,D14<=Unit_Data!$D$4+0.001),"OK","VIOL") -> OK | F14: =SUMPRODUCT(--(Daily_Plan!D14:G14>Crude_Data!$C$13:$F$13+0.001))+SUMPRODUCT(--(Daily_Plan!D14:G14<Crude_Data!$C$14:$F$14-0.001)) -> 0 | G14: =IF(F14=0,"OK","VIOL") -> OK | H14: =D14-D13 -> 0 | I14: =IF(ABS(H14)<=Unit_Data!$D$6+0.001,"OK","VIOL") -> OK | J14: =Daily_Plan!H14 -> 22 | K14: =IF(AND(J14>=Unit_Data!$D$9-0.001,J14<=Unit_Data!$D$8+0.001),"OK","VIOL") -> OK | L14: =IF(J14<=Daily_Plan!L14+0.001,"OK","VIOL") -> OK | M14: =Daily_Plan!I14 -> 32 | N14: =IF(AND(M14>=Unit_Data!$D$15-0.001,M14<=Unit_Data!$D$14+0.001),"OK","VIOL") -> OK | O14: =IF(M14<=Daily_Plan!O14+0.001,"OK","VIOL") -> OK | P14: =Daily_Plan!W14 -> 44.16 | Q14: =IF(AND(P14>=Unit_Data!$D$23-0.001,P14<=Unit_Data!$D$22+0.001),"OK","VIOL") -> OK | R14: =Daily_Plan!AD14 -> 95.157175 | S14: =IF(R14>=Unit_Data!$D$28-0.001,"OK","VIOL") -> OK | T14: =Daily_Plan!P14 -> 1.4610895 | U14: =IF(T14<=Unit_Data!$D$29+0.0001,"OK","VIOL") -> OK | V14: =COUNTIFS(Tank_Balance!$D$5:$D$314,A14,Tank_Balance!$L$5:$L$314,"<>OK") -> 0 | W14: =IF(V14=0,"OK","VIOL") -> OK | X14: =IF(COUNTIF(E14:W14,"VIOL")=0,"FEASIBLE","INFEASIBLE") -> FEASIBLE
A15: 11 | B15: =Daily_Plan!B15 -> 46306 | C15: =Daily_Plan!C15 -> Actual | D15: =Daily_Plan!J15 -> 150 | E15: =IF(AND(D15>=Unit_Data!$D$5-0.001,D15<=Unit_Data!$D$4+0.001),"OK","VIOL") -> OK | F15: =SUMPRODUCT(--(Daily_Plan!D15:G15>Crude_Data!$C$13:$F$13+0.001))+SUMPRODUCT(--(Daily_Plan!D15:G15<Crude_Data!$C$14:$F$14-0.001)) -> 0 | G15: =IF(F15=0,"OK","VIOL") -> OK | H15: =D15-D14 -> 0 | I15: =IF(ABS(H15)<=Unit_Data!$D$6+0.001,"OK","VIOL") -> OK | J15: =Daily_Plan!H15 -> 22 | K15: =IF(AND(J15>=Unit_Data!$D$9-0.001,J15<=Unit_Data!$D$8+0.001),"OK","VIOL") -> OK | L15: =IF(J15<=Daily_Plan!L15+0.001,"OK","VIOL") -> OK | M15: =Daily_Plan!I15 -> 32 | N15: =IF(AND(M15>=Unit_Data!$D$15-0.001,M15<=Unit_Data!$D$14+0.001),"OK","VIOL") -> OK | O15: =IF(M15<=Daily_Plan!O15+0.001,"OK","VIOL") -> OK | P15: =Daily_Plan!W15 -> 44.16 | Q15: =IF(AND(P15>=Unit_Data!$D$23-0.001,P15<=Unit_Data!$D$22+0.001),"OK","VIOL") -> OK | R15: =Daily_Plan!AD15 -> 95.157175 | S15: =IF(R15>=Unit_Data!$D$28-0.001,"OK","VIOL") -> OK | T15: =Daily_Plan!P15 -> 1.4610895 | U15: =IF(T15<=Unit_Data!$D$29+0.0001,"OK","VIOL") -> OK | V15: =COUNTIFS(Tank_Balance!$D$5:$D$314,A15,Tank_Balance!$L$5:$L$314,"<>OK") -> 0 | W15: =IF(V15=0,"OK","VIOL") -> OK | X15: =IF(COUNTIF(E15:W15,"VIOL")=0,"FEASIBLE","INFEASIBLE") -> FEASIBLE
A16: 12 | B16: =Daily_Plan!B16 -> 46307 | C16: =Daily_Plan!C16 -> Plan | D16: =Daily_Plan!J16 -> 150 | E16: =IF(AND(D16>=Unit_Data!$D$5-0.001,D16<=Unit_Data!$D$4+0.001),"OK","VIOL") -> OK | F16: =SUMPRODUCT(--(Daily_Plan!D16:G16>Crude_Data!$C$13:$F$13+0.001))+SUMPRODUCT(--(Daily_Plan!D16:G16<Crude_Data!$C$14:$F$14-0.001)) -> 0 | G16: =IF(F16=0,"OK","VIOL") -> OK | H16: =D16-D15 -> 0 | I16: =IF(ABS(H16)<=Unit_Data!$D$6+0.001,"OK","VIOL") -> OK | J16: =Daily_Plan!H16 -> 22 | K16: =IF(AND(J16>=Unit_Data!$D$9-0.001,J16<=Unit_Data!$D$8+0.001),"OK","VIOL") -> OK | L16: =IF(J16<=Daily_Plan!L16+0.001,"OK","VIOL") -> OK | M16: =Daily_Plan!I16 -> 32 | N16: =IF(AND(M16>=Unit_Data!$D$15-0.001,M16<=Unit_Data!$D$14+0.001),"OK","VIOL") -> OK | O16: =IF(M16<=Daily_Plan!O16+0.001,"OK","VIOL") -> OK | P16: =Daily_Plan!W16 -> 44.16 | Q16: =IF(AND(P16>=Unit_Data!$D$23-0.001,P16<=Unit_Data!$D$22+0.001),"OK","VIOL") -> OK | R16: =Daily_Plan!AD16 -> 95.157175 | S16: =IF(R16>=Unit_Data!$D$28-0.001,"OK","VIOL") -> OK | T16: =Daily_Plan!P16 -> 1.4610895 | U16: =IF(T16<=Unit_Data!$D$29+0.0001,"OK","VIOL") -> OK | V16: =COUNTIFS(Tank_Balance!$D$5:$D$314,A16,Tank_Balance!$L$5:$L$314,"<>OK") -> 0 | W16: =IF(V16=0,"OK","VIOL") -> OK | X16: =IF(COUNTIF(E16:W16,"VIOL")=0,"FEASIBLE","INFEASIBLE") -> FEASIBLE
A17: 13 | B17: =Daily_Plan!B17 -> 46308 | C17: =Daily_Plan!C17 -> Plan | D17: =Daily_Plan!J17 -> 150 | E17: =IF(AND(D17>=Unit_Data!$D$5-0.001,D17<=Unit_Data!$D$4+0.001),"OK","VIOL") -> OK | F17: =SUMPRODUCT(--(Daily_Plan!D17:G17>Crude_Data!$C$13:$F$13+0.001))+SUMPRODUCT(--(Daily_Plan!D17:G17<Crude_Data!$C$14:$F$14-0.001)) -> 0 | G17: =IF(F17=0,"OK","VIOL") -> OK | H17: =D17-D16 -> 0 | I17: =IF(ABS(H17)<=Unit_Data!$D$6+0.001,"OK","VIOL") -> OK | J17: =Daily_Plan!H17 -> 22 | K17: =IF(AND(J17>=Unit_Data!$D$9-0.001,J17<=Unit_Data!$D$8+0.001),"OK","VIOL") -> OK | L17: =IF(J17<=Daily_Plan!L17+0.001,"OK","VIOL") -> OK | M17: =Daily_Plan!I17 -> 32 | N17: =IF(AND(M17>=Unit_Data!$D$15-0.001,M17<=Unit_Data!$D$14+0.001),"OK","VIOL") -> OK | O17: =IF(M17<=Daily_Plan!O17+0.001,"OK","VIOL") -> OK | P17: =Daily_Plan!W17 -> 44.16 | Q17: =IF(AND(P17>=Unit_Data!$D$23-0.001,P17<=Unit_Data!$D$22+0.001),"OK","VIOL") -> OK | R17: =Daily_Plan!AD17 -> 95.157175 | S17: =IF(R17>=Unit_Data!$D$28-0.001,"OK","VIOL") -> OK | T17: =Daily_Plan!P17 -> 1.4610895 | U17: =IF(T17<=Unit_Data!$D$29+0.0001,"OK","VIOL") -> OK | V17: =COUNTIFS(Tank_Balance!$D$5:$D$314,A17,Tank_Balance!$L$5:$L$314,"<>OK") -> 0 | W17: =IF(V17=0,"OK","VIOL") -> OK | X17: =IF(COUNTIF(E17:W17,"VIOL")=0,"FEASIBLE","INFEASIBLE") -> FEASIBLE
... A35: 31 | B35: =Daily_Plan!B35 -> 46326 | C35: =Daily_Plan!C35 -> Plan | D35: =Daily_Plan!J35 -> 150 | E35: =IF(AND(D35>=Unit_Data!$D$5-0.001,D35<=Unit_Data!$D$4+0.001),"OK","VIOL") -> OK | F35: =SUMPRODUCT(--(Daily_Plan!D35:G35>Crude_Data!$C$13:$F$13+0.001))+SUMPRODUCT(--(Daily_Plan!D35:G35<Crude_Data!$C$14:$F$14-0.001)) -> 0 | G35: =IF(F35=0,"OK","VIOL") -> OK | H35: =D35-D34 -> 0 | I35: =IF(ABS(H35)<=Unit_Data!$D$6+0.001,"OK","VIOL") -> OK | J35: =Daily_Plan!H35 -> 22 | K35: =IF(AND(J35>=Unit_Data!$D$9-0.001,J35<=Unit_Data!$D$8+0.001),"OK","VIOL") -> OK | L35: =IF(J35<=Daily_Plan!L35+0.001,"OK","VIOL") -> OK | M35: =Daily_Plan!I35 -> 32 | N35: =IF(AND(M35>=Unit_Data!$D$15-0.001,M35<=Unit_Data!$D$14+0.001),"OK","VIOL") -> OK | O35: =IF(M35<=Daily_Plan!O35+0.001,"OK","VIOL") -> OK | P35: =Daily_Plan!W35 -> 44.16 | Q35: =IF(AND(P35>=Unit_Data!$D$23-0.001,P35<=Unit_Data!$D$22+0.001),"OK","VIOL") -> OK | R35: =Daily_Plan!AD35 -> 95.157175 | S35: =IF(R35>=Unit_Data!$D$28-0.001,"OK","VIOL") -> OK | T35: =Daily_Plan!P35 -> 1.4610895 | U35: =IF(T35<=Unit_Data!$D$29+0.0001,"OK","VIOL") -> OK | V35: =COUNTIFS(Tank_Balance!$D$5:$D$314,A35,Tank_Balance!$L$5:$L$314,"<>OK") -> 0 | W35: =IF(V35=0,"OK","VIOL") -> OK | X35: =IF(COUNTIF(E35:W35,"VIOL")=0,"FEASIBLE","INFEASIBLE") -> FEASIBLE
A37: Violations | E37: =COUNTIF(E5:E35,"VIOL") -> 0 | G37: =COUNTIF(G5:G35,"VIOL") -> 0 | I37: =COUNTIF(I5:I35,"VIOL") -> 0 | K37: =COUNTIF(K5:K35,"VIOL") -> 0 | L37: =COUNTIF(L5:L35,"VIOL") -> 0 | N37: =COUNTIF(N5:N35,"VIOL") -> 0 | O37: =COUNTIF(O5:O35,"VIOL") -> 0 | Q37: =COUNTIF(Q5:Q35,"VIOL") -> 0 | S37: =COUNTIF(S5:S35,"VIOL") -> 0 | U37: =COUNTIF(U5:U35,"VIOL") -> 0 | W37: =COUNTIF(W5:W35,"VIOL") -> 0 | X37: =SUM(E37,G37,I37,K37,L37,N37,O37,Q37,S37,U37,W37,E52) -> 0
A40: C14 – End-of-month inventory targets (closing 31-Oct ≥ target)
A41: Tank ID | B41: Service | C41: Closing 31-Oct | D41: Target | E41: C14 Check
A42: =Tank_Master!A4 -> TK-101 | B42: =Tank_Master!B4 -> Arab Light | C42: =Tank_Balance!I35 -> 569 | D42: =Tank_Master!G4 -> 400 | E42: =IF(C42>=D42-0.001,"OK","VIOL") -> OK
A43: =Tank_Master!A5 -> TK-102 | B43: =Tank_Master!B5 -> Murban | C43: =Tank_Balance!I66 -> 278 | D43: =Tank_Master!G5 -> 250 | E43: =IF(C43>=D43-0.001,"OK","VIOL") -> OK
A44: =Tank_Master!A6 -> TK-103 | B44: =Tank_Master!B6 -> Tapis | C44: =Tank_Balance!I97 -> 414 | D44: =Tank_Master!G6 -> 250 | E44: =IF(C44>=D44-0.001,"OK","VIOL") -> OK
A45: =Tank_Master!A7 -> TK-104 | B45: =Tank_Master!B7 -> Kimanis | C45: =Tank_Balance!I128 -> 159 | D45: =Tank_Master!G7 -> 150 | E45: =IF(C45>=D45-0.001,"OK","VIOL") -> OK
A46: =Tank_Master!A8 -> TK-201 | B46: =Tank_Master!B8 -> LPG | C46: =Tank_Balance!I159 -> 39.68 | D46: =Tank_Master!G8 -> 20 | E46: =IF(C46>=D46-0.001,"OK","VIOL") -> OK
A47: =Tank_Master!A9 -> TK-301 | B47: =Tank_Master!B9 -> Naphtha | C47: =Tank_Balance!I190 -> 102.98 | D47: =Tank_Master!G9 -> 50 | E47: =IF(C47>=D47-0.001,"OK","VIOL") -> OK
A48: =Tank_Master!A10 -> TK-401 | B48: =Tank_Master!B10 -> Gasoline 95 | C48: =Tank_Balance!I221 -> 172.76 | D48: =Tank_Master!G10 -> 150 | E48: =IF(C48>=D48-0.001,"OK","VIOL") -> OK
A49: =Tank_Master!A11 -> TK-501 | B49: =Tank_Master!B11 -> Jet A-1 | C49: =Tank_Balance!I252 -> 128.13 | D49: =Tank_Master!G11 -> 100 | E49: =IF(C49>=D49-0.001,"OK","VIOL") -> OK
A50: =Tank_Master!A12 -> TK-601 | B50: =Tank_Master!B12 -> Diesel B10 | C50: =Tank_Balance!I283 -> 196.0556 | D50: =Tank_Master!G12 -> 180 | E50: =IF(C50>=D50-0.001,"OK","VIOL") -> OK
A51: =Tank_Master!A13 -> TK-701 | B51: =Tank_Master!B13 -> Fuel Oil | C51: =Tank_Balance!I314 -> 231.67 | D51: =Tank_Master!G13 -> 100 | E51: =IF(C51>=D51-0.001,"OK","VIOL") -> OK
A52: C14 violations | E52: =COUNTIF(E42:E51,"VIOL") -> 0

Sheet Crude_Data
A1: Crude Slate & Assay Data
A2: Illustrative assay/price values for optimizer testing only – replace with site assay (LIMS/crude assay library) and current price deck.
A3: Property | B3: Unit | C3: Arab Light | D3: Murban | E3: Tapis | F3: Kimanis
A4: Crude price (delivered) | B4: $/bbl | C4: 76 | D4: 80.5 | E4: 84 | F4: 82.5
A5: Yield – LPG | B5: vol frac | C5: 0.02 | D5: 0.03 | E5: 0.03 | F5: 0.02
A6: Yield – SR Naphtha | B6: vol frac | C6: 0.18 | D6: 0.24 | E6: 0.22 | F6: 0.2
A7: Yield – Kerosene | B7: vol frac | C7: 0.14 | D7: 0.16 | E7: 0.17 | F7: 0.15
A8: Yield – SR Gasoil | B8: vol frac | C8: 0.2 | D8: 0.22 | E8: 0.3 | F8: 0.32
A9: Yield – Atm Residue | B9: vol frac | C9: 0.45 | D9: 0.34 | E9: 0.27 | F9: 0.3
A10: Yield – Loss / fuel | B10: vol frac | C10: 0.01 | D10: 0.01 | E10: 0.01 | F10: 0.01
A11: Yield closure check (must = 1.000) | B11: vol frac | C11: =SUM(C5:C10) -> 1 | D11: =SUM(D5:D10) -> 1 | E11: =SUM(E5:E10) -> 1 | F11: =SUM(F5:F10) -> 1
A12: Atm Residue sulfur | B12: wt% | C12: 3 | D12: 1.3 | E12: 0.15 | F12: 0.2
A13: Max CDU feed rate | B13: kbbl/d | C13: 60 | D13: 50 | E13: 50 | F13: 40
A14: Min CDU feed rate | B14: kbbl/d | C14: 0 | D14: 0 | E14: 0 | F14: 0
A15: Storage tank | B15: - | C15: TK-101 | D15: TK-102 | E15: TK-103 | F15: TK-104
A17: Notes
A18: • Yields are fixed CDU cut yields (vol) – linear model, no cut-point or severity optimisation.
A19: • Max CDU rate per crude reflects handling limits (e.g. waxy Kimanis, sour Arab Light corrosion window).
A20: • Residue sulfur is used in the residue-pool sulfur constraint (C10) – volumetric blending approximation.

Sheet Unit_Data
A1: Process Unit Constraints, Yields & Operating Cost
A2: Blue = editable parameter. Row numbers are referenced by formulas in Daily_Plan and Constraint_Check – do not insert rows.
A3: Unit | B3: Parameter | C3: Unit of measure | D3: Value | E3: Comment
A4: CDU | B4: Max throughput | C4: kbbl/d | D4: 150 | E4: Nameplate crude distillation capacity
A5: CDU | B5: Min throughput (turndown) | C5: kbbl/d | D5: 100 | E5: Furnace / column hydraulic turndown
A6: CDU | B6: Max day-to-day rate change | C6: kbbl/d | D6: 10 | E6: Ramp limit for stable operation
A7: CDU | B7: Variable opex | C7: $/bbl feed | D7: 1 | E7: Fuel, power, chemicals
A8: Reformer | B8: Max feed | C8: kbbl/d | D8: 25 | E8: CCR / semi-regen capacity
A9: Reformer | B9: Min feed | C9: kbbl/d | D9: 10 | E9: Min stable feed
A10: Reformer | B10: Variable opex | C10: $/bbl feed | D10: 2.5 | E10: Incl. catalyst & utilities
A11: Reformer | B11: Yield – Reformate | C11: vol frac | D11: 0.84
A12: Reformer | B12: Yield – LPG | C12: vol frac | D12: 0.08
A13: Reformer | B13: Yield – H2 / fuel gas (calc) | C13: vol frac | D13: =1-D11-D12 -> 0.08 | E13: Balance to 1.0 – consumed internally
A14: RFCC | B14: Max feed | C14: kbbl/d | D14: 35 | E14: Residue FCC capacity
A15: RFCC | B15: Min feed | C15: kbbl/d | D15: 15 | E15: Min stable feed
A16: RFCC | B16: Variable opex | C16: $/bbl feed | D16: 4 | E16: Catalyst, utilities
A17: RFCC | B17: Yield – FCC gasoline | C17: vol frac | D17: 0.52
A18: RFCC | B18: Yield – LPG | C18: vol frac | D18: 0.18
A19: RFCC | B19: Yield – LCO | C19: vol frac | D19: 0.18 | E19: Sent to DHT
A20: RFCC | B20: Yield – Slurry | C20: vol frac | D20: 0.06 | E20: Blended to fuel oil
A21: RFCC | B21: Yield – Coke / dry gas (calc) | C21: vol frac | D21: =1-SUM(D17:D20) -> 0.06 | E21: Balance to 1.0
A22: DHT | B22: Max feed | C22: kbbl/d | D22: 48 | E22: Diesel hydrotreater capacity
A23: DHT | B23: Min feed | C23: kbbl/d | D23: 20 | E23: Min stable feed
A24: DHT | B24: Variable opex | C24: $/bbl feed | D24: 1.5 | E24: H2, utilities
A25: DHT | B25: Yield – Diesel | C25: vol frac | D25: 0.98
A26: Blending | B26: RON – Reformate | C26: RON | D26: 98
A27: Blending | B27: RON – FCC gasoline | C27: RON | D27: 92
A28: Blending | B28: Gasoline pool RON min spec | C28: RON | D28: 95 | E28: Product spec (Gasoline 95)
A29: Blending | B29: Atm residue pool sulfur max | C29: wt% | D29: 1.5 | E29: RFCC feed / fuel oil sulfur limit

Sheet Product_Data
A1: Product Prices & Tankage Mapping
A2: Illustrative product netbacks for optimizer testing – replace with current price deck.
A3: Property | B3: Unit | C3: LPG | D3: Naphtha | E3: Gasoline 95 | F3: Jet A-1 | G3: Diesel B10 | H3: Fuel Oil
A4: Product price (netback) | B4: $/bbl | C4: 60 | D4: 74 | E4: 99 | F4: 103 | G4: 105 | H4: 72
A5: Storage tank | B5: - | C5: TK-201 | D5: TK-301 | E5: TK-401 | F5: TK-501 | G5: TK-601 | H5: TK-701
A6: Produced from | B6: - | C6: SR LPG + Reformer LPG + RFCC LPG | D6: SR Naphtha not sent to Reformer | E6: Reformate + FCC gasoline | F6: Kerosene (Merox) | G6: DHT product (SR gasoil + LCO) | H6: Unconverted residue + slurry

Sheet Tank_Master
A1: Tank Master Data
A2: Inventories in kbbl. Opening = start of 1-Oct-2026. End target applies to closing inventory on 31-Oct-2026 (constraint C14).
A3: Tank ID | B3: Service | C3: Type | D3: Working capacity (kbbl) | E3: Min heel (kbbl) | F3: Opening inv. 1-Oct (kbbl) | G3: End-of-month min target (kbbl) | H3: Notes
A4: TK-101 | B4: Arab Light | C4: Crude | D4: 1500 | E4: 150 | F4: 700 | G4: 400 | H4: Tank group (aggregated)
A5: TK-102 | B5: Murban | C5: Crude | D5: 1000 | E5: 100 | F5: 500 | G5: 250 | H5: Tank group (aggregated)
A6: TK-103 | B6: Tapis | C6: Crude | D6: 900 | E6: 90 | F6: 450 | G6: 250 | H6: Tank group (aggregated)
A7: TK-104 | B7: Kimanis | C7: Crude | D7: 800 | E7: 80 | F7: 380 | G7: 150 | H7: Tank group (aggregated)
A8: TK-201 | B8: LPG | C8: Product | D8: 60 | E8: 6 | F8: 30 | G8: 20 | H8: Product rundown + finished tank
A9: TK-301 | B9: Naphtha | C9: Product | D9: 250 | E9: 25 | F9: 110 | G9: 50 | H9: Product rundown + finished tank
A10: TK-401 | B10: Gasoline 95 | C10: Product | D10: 400 | E10: 40 | F10: 180 | G10: 150 | H10: Product rundown + finished tank
A11: TK-501 | B11: Jet A-1 | C11: Product | D11: 300 | E11: 30 | F11: 140 | G11: 100 | H11: Product rundown + finished tank
A12: TK-601 | B12: Diesel B10 | C12: Product | D12: 500 | E12: 50 | F12: 230 | G12: 180 | H12: Product rundown + finished tank
A13: TK-701 | B13: Fuel Oil | C13: Product | D13: 400 | E13: 40 | F13: 180 | G13: 100 | H13: Product rundown + finished tank

Sheet Crude_Receipts
A1: Crude Receipt Schedule (kbbl)
A2: Fixed cargo arrivals into crude tanks (parameter, not a decision variable).
A4: Day | B4: Date | C4: Arab Light | D4: Murban | E4: Tapis | F4: Kimanis
A5: 1 | B5: 46296 | C5: 0 | D5: 0 | E5: 0 | F5: 0
A6: 2 | B6: 46297 | C6: 0 | D6: 0 | E6: 0 | F6: 0
A7: 3 | B7: 46298 | C7: 0 | D7: 0 | E7: 0 | F7: 0
A8: 4 | B8: 46299 | C8: 0 | D8: 0 | E8: 0 | F8: 0
A9: 5 | B9: 46300 | C9: 0 | D9: 500 | E9: 0 | F9: 0
A10: 6 | B10: 46301 | C10: 0 | D10: 0 | E10: 400 | F10: 0
A11: 7 | B11: 46302 | C11: 0 | D11: 0 | E11: 0 | F11: 0
A12: 8 | B12: 46303 | C12: 600 | D12: 0 | E12: 0 | F12: 0
A13: 9 | B13: 46304 | C13: 0 | D13: 0 | E13: 0 | F13: 0
A14: 10 | B14: 46305 | C14: 0 | D14: 0 | E14: 0 | F14: 350
A15: 11 | B15: 46306 | C15: 0 | D15: 0 | E15: 0 | F15: 0
A16: 12 | B16: 46307 | C16: 0 | D16: 0 | E16: 0 | F16: 0
... A35: 31 | B35: 46326 | C35: 0 | D35: 0 | E35: 0 | F35: 0
A36: Total | C36: =SUM(C5:C35) -> 1100 | D36: =SUM(D5:D35) -> 1000 | E36: =SUM(E5:E35) -> 1200 | F36: =SUM(F5:F35) -> 700

Sheet Product_Liftings
A1: Product Lifting Schedule (kbbl)
A2: Daily pipeline/truck liftings plus vessel cargoes (parameter, not a decision variable).
A4: Day | B4: Date | C4: LPG | D4: Naphtha | E4: Gasoline 95 | F4: Jet A-1 | G4: Diesel B10 | H4: Fuel Oil
A5: 1 | B5: 46296 | C5: 9 | D5: 0 | E5: 30 | F5: 18 | G5: 35 | H5: 0
A6: 2 | B6: 46297 | C6: 9 | D6: 0 | E6: 30 | F6: 18 | G6: 35 | H6: 0
A7: 3 | B7: 46298 | C7: 9 | D7: 0 | E7: 30 | F7: 18 | G7: 35 | H7: 0
A8: 4 | B8: 46299 | C8: 9 | D8: 0 | E8: 30 | F8: 18 | G8: 35 | H8: 0
A9: 5 | B9: 46300 | C9: 9 | D9: 0 | E9: 30 | F9: 18 | G9: 35 | H9: 0
A10: 6 | B10: 46301 | C10: 9 | D10: 0 | E10: 30 | F10: 18 | G10: 35 | H10: 200
A11: 7 | B11: 46302 | C11: 9 | D11: 0 | E11: 30 | F11: 103 | G11: 35 | H11: 0
A12: 8 | B12: 46303 | C12: 9 | D12: 0 | E12: 30 | F12: 18 | G12: 35 | H12: 0
A13: 9 | B13: 46304 | C13: 9 | D13: 100 | E13: 30 | F13: 18 | G13: 35 | H13: 0
A14: 10 | B14: 46305 | C14: 39 | D14: 0 | E14: 30 | F14: 18 | G14: 35 | H14: 0
A15: 11 | B15: 46306 | C15: 9 | D15: 0 | E15: 30 | F15: 18 | G15: 175 | H15: 0
A16: 12 | B16: 46307 | C16: 9 | D16: 0 | E16: 110 | F16: 18 | G16: 35 | H16: 0
... A35: 31 | B35: 46326 | C35: 9 | D35: 0 | E35: 30 | F35: 18 | G35: 35 | H35: 0
A36: Total | C36: =SUM(C5:C35) -> 339 | D36: =SUM(D5:D35) -> 300 | E36: =SUM(E5:E35) -> 1090 | F36: =SUM(F5:F35) -> 728 | G36: =SUM(G5:G35) -> 1365 | H36: =SUM(H5:H35) -> 600
